Workbook

Sheet Targets
A1: company | B1: url | C1: country | D1: segment | E1: sub_segment | F1: category | G1: description | H1: stage_funding | I1: est_size | J1: pain_evidence | K1: score_breakdown | L1: score | M1: wave | N1: owner | O1: first_line | P1: research_hook | Q1: verify_before_sending | R1: contacts | S1: n_contacts | T1: contact_email | U1: touch1_date | V1: followup_date | W1: breakup_date | X1: replied | Y1: call_booked | Z1: call_held | AA1: partner_status | AB1: notes
A2: EXAMPLE - Acme SaaS | B2: acme.example | C2: Germany | D2: EU vertical | F2: Vertical SaaS | L2: 9 | M2: 1 | N2: Ivica | O2: Example hook referencing their specific evidence. | Q2: Example caveat to check first | R2: Jane Doe (CTO) | S2: =COUNTIF(Contacts!$A:$A,A2) -> 0 | T2: jane@acme.example | U2: 2026-08-04 | V2: 2026-08-08 | W2: 2026-08-14 | X2: Y | Y2: 2026-08-11 | Z2: 2026-08-12 | AA2: discovery call held | AB2: asked about SOC2; send follow-up deck
A3: Attio | B3: attio.com | C3: UK | D3: Dev tools | F3: Sales/CRM | G3: AI-native CRM for GTM teams | H3: Series B $52M GV, Aug 2025 (blog (https://attio.com/blog/attio-raises-52m-series-b)) | I3: ~84 (Tracxn (https://tracxn.com/d/companies/attio/__zXaorGoGUFFCntq5i6GuYbFjA5y0l4NPgP5t1R3FhXg)) | J3: G2: native library ~8 apps vs HubSpot 1,500+; "Some more native integrations would be good so I don't have to use Zapier" (G2 (https://www.g2.com/products/attio/reviews?qs=pros-and-cons)); /apps 403 | K3: 2/2/3/2/1 | L3: 10 | M3: 1 | N3: Ivica | O3: Your G2 reviews' most consistent complaint is the native-integration gap versus HubSpot's 1500-app marketplace - close it white-label. | P3: Your G2 reviews' most consistent complaint is the native-integration gap versus HubSpot's 1,500-app marketplace - we build an open-source embedded iPaaS that lets an 84-person team close that gap white-label instead of hand-coding each connector. | Q3: Apps page 403 during research | S3: =COUNTIF(Contacts!$A:$A,A3) -> 0
A4: folk | B4: folk.app | C4: France | D4: Dev tools | F4: Sales/CRM | G4: Lightweight CRM for agencies/founders | H4: Series A $33M Bessemer per aggregators (PitchBook (https://pitchbook.com/profiles/company/228251-62)) - primary not fetched | I4: 20–55 (getlatka (https://getlatka.com/companies/folk.app/team)) | J4: Native integrations limited to Gmail/Outlook/LinkedIn/WhatsApp; "4,900+ integrations" are via Zapier/Make; G2/Capterra flag limited native integrations, no Salesforce sync (capsulecrm review (https://capsulecrm.com/blog/folk-crm-alternatives/), G2 (https://www.g2.com/products/folk-folk/reviews?qs=pros-and-cons)) | K4: 2/2/3/2/1 | L4: 10 | M4: 1 | N4: Ivica | O4: Reviewers keep dinging folk for four native integrations and pushing the rest through customers' paid Zapier plans - ship the Salesforce/HubSpot syncs they ask for. | P4: Reviewers keep dinging folk for having only four native integrations and pushing everything else through your customers' paid Zapier plans - an embedded open-source iPaaS could let you ship the Salesforce/HubSpot syncs they're asking for without staffing a connector team. | Q4: Funding figure via aggregators - verify | S4: =COUNTIF(Contacts!$A:$A,A4) -> 0
A5: Cargoson | B5: cargoson.com | C5: Estonia | D5: EU vertical | F5: Logistics (TMS) | G5: Cloud TMS consolidating carrier booking/rates/tracking | H5: Bootstrapped (Getlatka (https://getlatka.com/companies/cargoson.com)) | I5: ~13 emp (Getlatka (https://getlatka.com/companies/cargoson.com)) | J5: Core product = integration surface: 2,000+ carrier integrations + ERP connectors maintained by ~13 people (cargoson.com (https://www.cargoson.com/en)); /integrations 403 | K5: 2/2/3/2/1 | L5: 10 | M5: 1 | N5: Co-founder | O5: A 13-person team maintaining 2000+ carrier and ERP connectors - we build the embedded engine that ships connectors without hand-coding each one. | P5: Noticed your 13-person team maintains 2,000+ carrier and ERP connectors - we build the embedded integration engine that lets teams like yours ship new connectors without hand-coding each one. | Q5: Integrations page 403 during research | S5: =COUNTIF(Contacts!$A:$A,A5) -> 0
A6: Vertuoza | B6: vertuoza.com | C6: Belgium | D6: EU vertical | F6: Construction | G6: Quote-to-invoice SaaS for SMB contractors (BE/FR/LU/CH) | H6: Series A €10M, 2023 (Fortino (https://www.fortino.vc/news/vertuoza-reinforces-its-growth-ambitions-and-successfully-concludes-its-10-million-eu-series)) | I6: ~110–123 (LeadIQ (https://leadiq.com/c/vertuoza/601737cf411f372b409a11b2)) | J6: Outsourced accounting integrations to Chift (case study (https://www.chift.eu/case-studies/how-vertuoza-unlocked-accounting-automation-with-chifts-integrations)); review notes limited native integrations, no public API/Zapier (Skello (https://www.skello.io/blog/avis-vertuoza-alternatives)) | K6: 2/2/3/2/1 | L6: 10 | M6: 1 | N6: Co-founder | O6: You solved accounting sync via Chift's unified API - get the same self-serve depth across banking, suppliers and ERP under your own brand. | P6: Saw you solved accounting sync via Chift's unified API - an embedded iPaaS would let you offer the same self-serve depth across banking, suppliers and ERP connectors beyond accounting, under your own brand. | S6: =COUNTIF(Contacts!$A:$A,A6) -> 0
A7: Humaans | B7: humaans.io | C7: UK | D7: HR/fin-ops | F7: HRIS | G7: API-first employee-data hub / HRIS for fast-growing SMBs | H7: Series A $15M, Oct 2022 (TechCrunch (https://techcrunch.com/2022/10/04/humaans-raises-15m-to-simplify-hr-tasks-like-onboarding/)) | I7: ~34–53 emp (Latka (https://getlatka.com/companies/humaans.io), PitchBook (https://pitchbook.com/profiles/company/442747-00)) | J7: Reviewers: "integration support is minimal, few built-in connectors", Lattice sync is one-way, users requesting Deel integration (Research.com (https://research.com/software/reviews/humaans), SoftwareFinder (https://softwarefinder.com/hr/humaans/reviews)) | L7: 10 | M7: 1 | N7: Ivica | O7: Reviewers call integration support 'minimal' and ask for Deel plus true two-way Lattice sync - exactly the long tail an embedded iPaaS closes without a connectors team. | P7: Your G2 reviewers love Humaans but call integration support 'minimal' and are asking for Deel and true two-way Lattice sync - that's exactly the long tail an embedded iPaaS closes without hiring a connectors team. | Q7: Re-verify review quotes on G2/Capterra; UK counted for EU bonus | S7: =COUNTIF(Contacts!$A:$A,A7) -> 0
A8: Kenjo | B8: kenjo.io | C8: Germany | D8: HR/fin-ops | F8: HRIS (frontline/SMB) | G8: All-in-one HR for frontline & SMB workforces (DE/ES/LatAm) | H8: Series A €8.8M, Sep 2023 (Tech.eu (https://tech.eu/2023/09/18/berlin-based-kenjo-8-8m-hrtech-to-latin-america/)) | I8: ~71–98 emp (Tracxn (https://tracxn.com/d/companies/kenjo/__V7FbYPAoSJt0jRXHCCyaW3ciVaB5yeoJmRr7d7o_ao8), PitchBook (https://pitchbook.com/profiles/company/92904-13)) | J8: "Integration with third-party software is limited"; 3.8/5 on integrations; payroll depends on DATEV/third-party connections; users asking deeper Slack integration (Research.com (https://research.com/software/reviews/kenjo), rfp.wiki (https://www.rfp.wiki/hr-office/hcm-suites-1000-employee-enterprises/hris-systems/kenjo), Capterra (https://capterra.com/p/165837/kenjo/reviews/)) | L8: 10 | M8: 1 | N8: Ivica | O8: Payroll runs through DATEV bridges yet reviewers rate integrations 3.8/5 - ship the Slack/payroll connectors users keep asking for. | P8: Kenjo's payroll story runs through DATEV and partner connections, yet reviewers still rate your third-party integrations 3.8/5 - an embedded integration layer would let you ship the Slack/payroll connectors users keep asking for. | S8: =COUNTIF(Contacts!$A:$A,A8) -> 0
A9: Cal.com | B9: cal.com | C9: USA | D9: Dev tools | F9: Dev tools / scheduling | G9: Open-source scheduling infrastructure | H9: Series A $25M, 2022 (VentureBeat (https://venturebeat.com/business/open-source-calendly-rival-cal-com-raises-25m)) | I9: ~44 (Tracxn (https://tracxn.com/d/companies/calcom/__IEeuL9zwIQRcTDpJAAntiwKZ0CItPOOlE9FD_QgbF4o)) | J9: 43 open "integration" issues across org; Zoho Meeting request calls Zapier workaround "cumbersome and error-prone" (#19305 (https://github.com/calcom/cal.diy/issues/19305)) | K9: 2/2/3/2/0 | L9: 9 | M9: 1 | N9: Ivica | O9: There are 43 open integration requests across your GitHub org, with users calling the Zapier workaround 'cumbersome and error-prone'. | P9: There are 43 open integration requests across your GitHub org, with users calling the Zapier workaround 'cumbersome and error-prone' - open-source to open-source, ByteChef could power those long-tail app-store connectors so your core team stays on scheduling. | S9: =COUNTIF(Contacts!$A:$A,A9) -> 0
A10: Chatwoot | B10: chatwoot.com | C10: USA | D10: Dev tools | F10: Customer support | G10: Open-source omnichannel support platform | H10: Seed $1.6M, YC W21 (Tracxn (https://tracxn.com/d/companies/chatwoot/__aRgDQ9vdvJArJxEw66gaFsL2oc8vTbzfUwPrEf6mpIo)) | I10: 10–12 (YC (https://www.ycombinator.com/companies/chatwoot)) | J10: Discord integration open since 2021, 34 reactions (#1941 (https://github.com/chatwoot/chatwoot/issues/1941)); MS Teams since 2021 (#1655 (https://github.com/chatwoot/chatwoot/issues/1655)); HubSpot since 2020 (#1197 (https://github.com/chatwoot/chatwoot/issues/1197)) | K10: 2/2/3/2/0 | L10: 9 | M10: 1 | N10: Ivica | O10: Your Discord, Teams and HubSpot integration issues have been open 4-5 years with dozens of upvotes - open-source to open-source, clear the backlog. | P10: Your Discord, Teams, and HubSpot integration issues have been open for 4-5 years with dozens of upvotes - as a fellow open-source company we'd love to show how embedding ByteChef could clear that backlog without growing your 12-person team. | S10: =COUNTIF(Contacts!$A:$A,A10) -> 0
A11: ilert | B11: ilert.com | C11: Germany | D11: Dev tools | F11: Incident management | G11: AI-first incident management / on-call | H11: Bootstrapped, ~$1.4M ARR (getlatka (https://getlatka.com/companies/ilert.com)) | I11: ~13 (getlatka (https://getlatka.com/companies/ilert.com)) | J11: Changelog shows team hand-shipping integrations monthly (Dynatrace, Raygun) (changelog (https://docs.ilert.com/changelog)) | K11: 2/2/2/2/1 | L11: 9 | M11: 1 | N11: Ivica | O11: A 13-person bootstrapped team hand-building Dynatrace and Raygun integrations monthly - match PagerDuty's catalog without PagerDuty's headcount. | P11: Your changelog shows a 13-person bootstrapped team hand-building Dynatrace and Raygun integrations month after month - embedding an open-source iPaaS could let ilert match PagerDuty's catalog without PagerDuty's headcount. | S11: =COUNTIF(Contacts!$A:$A,A11) -> 0
A12: Twenty | B12: twenty.com | C12: France | D12: Dev tools | F12: Sales/CRM | G12: Open-source CRM (Salesforce alt), YC S23 | H12: Series A $38M Nov 2025 (Tracxn (https://tracxn.com/d/companies/twenty/__oyf_sCMiigApXb-QCd9gzMXlCdKb6Za7OSNrSEGQJ7E)) | I12: unknown | J12: Users: missing PostHog integration "is one of the issues blocking leaving HubSpot" (Discussion #16735 (https://github.com/twentyhq/twenty/discussions/16735)) | K12: 2/1/3/2/1 | L12: 9 | M12: 1 | N12: Ivica | O12: In your Native Integrations discussion, users say the missing PostHog connector blocks leaving HubSpot - ship that long tail inside Twenty. | P12: In your Native Integrations discussion, users say the missing PostHog connector is literally what blocks them from leaving HubSpot - ByteChef is an open-source embedded iPaaS (AGPL-friendly, self-hostable) that could ship that long tail inside Twenty. | Q12: Headcount unknown | S12: =COUNTIF(Contacts!$A:$A,A12) -> 0
A13: Doctorly | B13: doctorly.de | C13: Germany | D13: EU vertical | F13: Health (PVS) | G13: Cloud practice management for German medical practices | H13: Series A $17.2M total (Tech.eu (https://tech.eu/2023/03/01/berlin-based-health-tech-startup-doctorly-diagnoses-10-million/), Silicon Canals (https://siliconcanals.com/doctorly-raises-6-7m/)) | I13: ~58 (ZoomInfo (https://www.zoominfo.com/c/doctorly-gmbh/507136489)) | J13: Heavy regulated integration load (TI, GDT/DICOM); positions "integration platform for wider health industry" as product (The SaaS News (https://www.thesaasnews.com/news/doctorly-raises-10-million-in-series-a)) | K13: 2/2/2/2/1 | L13: 9 | M13: 1 | N13: Co-founder | O13: You describe doctorly as including an integration platform for the wider health industry - we provide exactly that layer, open-source and embeddable. | P13: You've described doctorly as including an integration platform for the wider health industry - we provide exactly that layer (open-source, embeddable) so your ~60-person team doesn't have to build connector infrastructure from scratch. | S13: =COUNTIF(Contacts!$A:$A,A13) -> 0
A14: Nelly | B14: getnelly.de | C14: Germany | D14: EU vertical | F14: Health (practice fintech) | G14: Financial OS for medical/dental practices | H14: Series B €50M, Jan 2025 (Tech.eu (https://tech.eu/2025/01/15/berlin-s-nelly-raises-50m-series-b-to-free-medical-practices-from-tedious-bureaucracy/)) | I14: unknown (1,200+ practices) | J14: Built own "Nelly Connector" to bridge into "any practice software" - per-PVS plumbing maintained in-house (Connector (https://www.getnelly.de/en/software-solutions/connector), partners (https://www.getnelly.de/en/partners)) | K14: 2/1/3/2/1 | L14: 9 | M14: 1 | N14: Co-founder | O14: The Nelly Connector speaks to every German PVS one interface at a time - turn that connector backlog into configuration instead of engineering. | P14: Your Nelly Connector has to speak to every German PVS one interface at a time - an embedded integration platform could turn that connector backlog into configuration instead of engineering. | Q14: Headcount unknown | S14: =COUNTIF(Contacts!$A:$A,A14) -> 0
A15: Payaca | B15: payaca.com | C15: UK | D15: EU vertical | F15: Field service (clean-tech trades) | G15: CRM/job management for solar & heat-pump installers | H15: Seed £331k Blackfinch 2021 (PE Wire (https://www.privateequitywire.co.uk/payaca-secures-gbp331k-investment-blackfinch/)) | I15: unknown (small) | J15: Four native connectors (QuickBooks, Xero, OpenSolar, Heatpunk), rest via Zapier (integrations (https://payaca.com/us/features/integrations)); 403, from indexed copy | K15: 2/1/3/2/1 | L15: 9 | M15: 1 | N15: Co-founder | O15: Four native connectors and Zapier for the rest - ship white-label native integrations (MCS bodies, suppliers, accounting) without per-connector engineering. | P15: Your integrations page lists four native connectors and leans on Zapier for the rest - we help vertical SaaS teams ship white-label native integrations (MCS bodies, suppliers, accounting) without per-connector engineering. | Q15: Size unverified; last disclosed round stale | S15: =COUNTIF(Contacts!$A:$A,A15) -> 0
A16: Plancraft | B16: plancraft.com | C16: Germany | D16: EU vertical | F16: Construction (trades) | G16: Cloud software for craft businesses; 20k+ customers | H16: Series B €38M, Aug 2025 (EU-Startups (https://www.eu-startups.com/2025/08/e38-million-for-german-saas-startup-plancraft-to-lead-ai-transformation-in-european-construction/)) | I16: ~117–141 (Getlatka (https://getlatka.com/companies/plancraft.com)) | J16: Integration story file-based: DATEV via CSV, otherwise GAEB/DATANORM exchange formats (Schnittstellen (https://plancraft.com/de-de/funktionen/software-schnittstellen)) | K16: 2/2/2/2/1 | L16: 9 | M16: 1 | N16: Co-founder | O16: Your DATEV workflow still runs on CSV export/import while you scale to 11 countries - get real two-way accounting and supplier APIs. | P16: Your DATEV workflow is still CSV export/import - as you scale across 11 countries, an embedded integration platform gets you real two-way accounting and supplier APIs without growing an integrations team. | R16: Julian Wiedenhaus (CEO & Co-founder) | S16: =COUNTIF(Contacts!$A:$A,A16) -> 1
A17: Atlar | B17: atlar.com | C17: Sweden | D17: HR/fin-ops | F17: Treasury / fin-ops | G17: Treasury & payments platform on direct bank connectivity | H17: Seed €5M, Nov 2022; $13.5M total (FinSMEs (https://www.finsmes.com/2022/11/atlar-raises-e5m-in-seed-funding.html), Atlar (https://www.atlar.com/company)) | I17: unknown (seed-to-A scale) | J17: Dedicated "Connectivity" team of 7 engineers growing to 9 that "builds and operates the integrations that connect Atlar to the world's banks"; hiring an EM for it (Atlar careers (https://careers.atlar.com/jobs/7898497-engineering-manager-connectivity)) | L17: 9 | M17: 1 | N17: Ivica | O17: You are staffing a nine-engineer Connectivity team for bank/ERP integrations - worth comparing what an embedded open-source layer takes off that roadmap. | P17: You're staffing a nine-engineer Connectivity team just to keep bank and ERP integrations alive - worth comparing what an embedded, open-source integration layer could take off that roadmap. | Q17: Headcount unknown | R17: Johannes Elgh (CTO & Co-founder) | S17: =COUNTIF(Contacts!$A:$A,A17) -> 1
A18: Hyperline | B18: hyperline.co | C18: France | D18: HR/fin-ops | F18: Billing / revenue | G18: SMB-focused billing & subscription platform | H18: Seed ~$14M total (incl. $10M ext, Jan 2025) (Tech.eu (https://tech.eu/2025/01/16/hyperline-raises-10m-for-automated-billing/)) | I18: unknown (seed scale) | J18: Changelog shows accounting/payment connectors shipped one at a time by the core team: Zoho Books (Mar 2026), Adyen (Apr 2026), Rillet + NetSuite (May 2026) (changelog (https://docs.hyperline.co/changelog/2026-03)); integrations page not verifiable (403) | L18: 9 | M18: 1 | N18: Ivica | O18: Your changelog shows accounting connectors shipped one at a time (Zoho Books in March, NetSuite/Rillet in May) - announce ten a quarter without burning core eng. | P18: Your changelog shows the team shipping accounting connectors one by one - Zoho Books in March, NetSuite and Rillet in May - an embedded iPaaS would let you announce ten of those a quarter without burning core eng cycles. | Q18: Headcount unknown; integrations page 403 during research | R18: Clément Garbay (Co-founder & CTO) | S18: =COUNTIF(Contacts!$A:$A,A18) -> 1
A19: Payslip | B19: payslip.com | C19: Ireland | D19: HR/fin-ops | F19: Global payroll control | G19: Vendor-agnostic global-payroll control layer over HCM + local payroll providers | H19: Series A ~€2.7M + $10M extension, 2020–21; growth financing May 2026 (PR Newswire (https://www.prnewswire.com/news-releases/payslip-adds-10m-to-its-series-a-financing-to-disrupt-traditional-service-model-for-global-payroll-301293783.html), PR Newswire 2026 (https://www.prnewswire.com/news-releases/payslip-secures-growth-financing-to-scale-ai-global-payroll-platform-302783394.html)) | I19: unknown (150-hire plan announced 2021, Silicon Canals (https://siliconcanals.com/payslip-raises-8-3m/)) | J19: Business model *is* connectors: in-house "Integrations as a Service specialists" hand-built the Workday PECI multi-country connector and SuccessFactors integrations (Payslip blog (https://payslip.com/resources/blog/fastest-payroll-integration-in-workday-history-yes-we-did), Payslip Connect (https://payslip.com/product/payslip-connect)) | L19: 9 | M19: 1 | N19: Ivica | O19: Your team hand-builds every HCM-to-payroll connector (Workday PECI, SuccessFactors) - the workload an embedded platform turns into configuration. | P19: Your team hand-builds every HCM-to-payroll connector - Workday PECI, SuccessFactors and beyond - which is precisely the workload an embedded integration platform turns from custom engineering into configuration. | Q19: Headcount unknown | R19: Fidelma McGuirk (Founder & CEO) | S19: =COUNTIF(Contacts!$A:$A,A19) -> 1
A20: Sequence | B20: sequencehq.com | C20: UK | D20: HR/fin-ops | F20: Billing / CPQ / AR | G20: AI billing, quoting and AR automation for B2B finance teams | H20: Series A $20M, Dec 2025; $38M total (PYMNTS (https://www.pymnts.com/news/investment-tracker/2025/sequence-raises-20-million-for-ai-powered-billing-automation/)) | I20: unknown (Series A scale) | J20: Only QuickBooks Online and Xero are native two-way accounting syncs; NetSuite handled via "NetSuite-compatible invoice exports" and "get in touch with our team" (docs - NetSuite (https://docs.sequencehq.com/integrations/netsuite), Xero (https://docs.sequencehq.com/integrations/xero)) | L20: 9 | M20: 1 | N20: Ivica | O20: Your docs route NetSuite customers to CSV exports and 'talk to our team' - make NetSuite and the next ten ERPs native. | P20: Your docs still route NetSuite customers to CSV invoice exports and a 'talk to our team' link - embedding a white-label integration layer would make NetSuite (and the next ten ERPs) native without a connectors squad. | Q20: Headcount unknown | R20: Riya Grover (Co-founder & CEO) | S20: =COUNTIF(Contacts!$A:$A,A20) -> 1
A21: Zelt | B21: zelt.app | C21: UK | D21: HR/fin-ops | F21: HR / payroll / IT ops | G21: All-in-one HR, payroll and device management for SMBs | H21: Seed $3.5M (2022) + $6M (Jan 2025), $13.2M total (EU-Startups (https://www.eu-startups.com/2025/01/hrtech-zelt-raises-e5-7-million-to-fix-people-operations-once-and-for-all/)) | I21: unknown (seed scale) | J21: Reviews flag "lack of a comprehensive integration ecosystem or a public API", syncing issues with Nest pensions, manual bank-file edits for payroll (hr.software (https://www.hr.software/reviews/zelt), Research.com (https://research.com/software/reviews/zelt)) | L21: 9 | M21: 1 | N21: Ivica | O21: Reviews flag the missing integration ecosystem and public API - an embedded iPaaS gives you both, plus fixes like the Nest pension sync. | P21: Reviewers praise Zelt's all-in-one scope but call out the missing integration ecosystem and public API - an embedded iPaaS would give you both, plus fixes for pain points like the Nest pension sync, in one move. | Q21: Headcount unknown | R21: Chris Priebe (Co-founder & CEO) | S21: =COUNTIF(Contacts!$A:$A,A21) -> 1
A22: Coperniq | B22: coperniq.io | C22: USA | D22: US vertical | F22: Energy/solar contractor software | G22: Workflow + CRM for solar/energy contractors (YC W23) | H22: Seed $4M, Nov 2023 (TechCrunch (https://techcrunch.com/2023/11/06/coperniq-seed-round/)) | J22: Support docs show ~8 native integrations, rest "mediated via Zapier" (support docs (https://support.coperniq.io/integrations/quickbooks-online-and-desktop-integration)); /integrations 403 | L22: 9 | M22: 1 | N22: Co-founder | O22: Your support docs list about eight native integrations with the rest routed through Zapier - ship the long tail natively and white-labeled. | P22: Your support docs list about eight native integrations with the rest routed through Zapier - ByteChef lets solar-software teams ship the long tail natively and white-labeled without burning sprint time. | Q22: Integrations page 403 during research | R22: Abdullah Al-Zandani (CEO) | S22: =COUNTIF(Contacts!$A:$A,A22) -> 1
A23: Latchel | B23: latchel.com | C23: USA | D23: US vertical | F23: Proptech - maintenance ops | G23: Maintenance ops + resident amenities for property managers (YC) | H23: Series A $16.7M, Jul 2022 (FinSMEs (https://www.finsmes.com/2022/07/latchel-raises-16-7m-in-series-a-funding.html)) | J23: Series A PR earmarks funds to "deepen third party property management integrations" (PR Newswire (https://www.prnewswire.com/news-releases/latchel-closes-16-7-million-to-enhance-resident-services-and-maintenance-workflow-301593940.html)) | L23: 9 | M23: 1 | N23: Co-founder | O23: Your Series A announcement earmarked funds to 'deepen third party property management integrations' - compress that roadmap from quarters to weeks. | P23: Your Series A announcement earmarked funds to 'deepen third party property management integrations' - that is exactly the roadmap an embedded iPaaS compresses from quarters to weeks. | R23: Ethan Lieber (CEO & Co-founder) | S23: =COUNTIF(Contacts!$A:$A,A23) -> 1
A24: Lawmatics | B24: lawmatics.com | C24: USA | D24: US vertical | F24: Legal - CRM/intake | G24: Legal CRM, intake, marketing automation for law firms | H24: Series A $10M, Dec 2021 (GlobeNewswire (https://www.globenewswire.com/news-release/2021/12/15/2353012/0/en/lawmatics-raises-10m-in-series-a-funding-to-change-the-way-lawyers-drive-business.html)) | J24: G2: "weak in billing, time tracking, document management, and integrations" (G2 (https://www.g2.com/products/lawmatics/reviews?qs=pros-and-cons)); Zapier as workaround (help center (https://help.lawmatics.com/en/articles/10699986-lawmatics-zapier-app-overview)) | L24: 9 | M24: 1 | N24: Co-founder | O24: G2 reviewers praise your automation but repeatedly flag integrations as a weak spot - close the gap without staffing a connector team. | P24: G2 reviewers praise Lawmatics' automation but repeatedly flag integrations as a weak spot - an embedded iPaaS would close that gap without you staffing a dedicated connector team. | R24: Matt Spiegel (Founder & CEO) | S24: =COUNTIF(Contacts!$A:$A,A24) -> 1
A25: Checkly | B25: checklyhq.com | C25: Germany | D25: Dev tools | F25: Observability | G25: Code-first synthetic monitoring | H25: Series B $20M Balderton Jul 2024 (blog (https://www.checklyhq.com/blog/announcing-20m-to-enable-engineers-to-detect-and-r/)) | I25: ~58 (Tracxn (https://tracxn.com/d/companies/checkly/__Tm43V0cikPcbX150mT8CmGxTOlmV1N5Fpmh-A6aB-V4)) | J25: Public-roadmap alert-channel requests (OpsGenie #18 (https://github.com/checkly/public-roadmap/issues/18)); modest channel set (docs (https://www.checklyhq.com/docs/communicate/alerts/channels/)); /integrations 403 | K25: 2/2/1/2/1 | L25: 8 | M25: 2 | N25: Ivica | O25: Your alert-channel list is a fraction of Datadog's and the community has filed integration requests for years - catalog breadth at startup cost. | P25: Checkly's alert-channel list is still a fraction of what Datadog offers and your community has been filing integration requests since the public-roadmap days - an embedded open-source iPaaS could give you their catalog breadth at Berlin-startup cost. | Q25: Feedback board and integrations page 403 during research | R25: Hannes Lenke (CEO) | S25: =COUNTIF(Contacts!$A:$A,A25) -> 1
A26: Infisical | B26: infisical.com | C26: USA | D26: Dev tools | F26: Security | G26: Open-source secrets/identity management | H26: Series A $16M Jun 2025 (PR Newswire (https://www.prnewswire.com/news-releases/infisical-secures-16m-series-a-to-redefine-enterprise-secrets-identity-and-access-management-302475063.html)) | I26: ~20–50 (Startup Intros (https://startupintros.com/orgs/infisical)) | J26: Native-sync bugs open for years: duplicate syncs since May 2023 (#611 (https://github.com/Infisical/infisical/issues/611)), GitLab masked-sync since Jun 2024 (#2035 (https://github.com/Infisical/infisical/issues/2035)) | K26: 2/2/2/2/0 | L26: 8 | M26: 2 | N26: Ivica | O26: Secret-sync bugs like the GitLab masked-sync failure sit open since 2024 across your hand-built connector fleet - we maintain 190+ so yours do not rot. | P26: Secret-sync integrations are core to Infisical, yet bugs like the GitLab masked-sync failure have sat open since 2024 across your hand-built connector fleet - a fellow open-source team, we maintain 190+ connectors so yours don't rot. | R26: Maidul Islam (Co-founder) | S26: =COUNTIF(Contacts!$A:$A,A26) -> 1
A27: Plane | B27: plane.so | C27: India/USA | D27: Dev tools | F27: Project management | G27: Top open-source PM tool (Jira alt) | H27: Seed $4M OSS Capital 2024 (blog (https://plane.so/blog/plane-raises-4m-seed)) | I27: unknown | J27: Gitea sync open since Jul 2023, 94 reactions (#1495 (https://github.com/makeplane/plane/issues/1495)); GitLab parity (#8088 (https://github.com/makeplane/plane/issues/8088)); Mattermost (#6001 (https://github.com/makeplane/plane/issues/6001)) | K27: 2/1/3/2/0 | L27: 8 | M27: 2 | N27: Ivica | O27: Your Gitea-sync issue has 94 upvotes since 2023 with GitLab parity and Mattermost queued behind it - power those syncs, keep engineers on core PM. | P27: Your Gitea-sync issue has 94 upvotes and has sat open since 2023 while GitLab parity and Mattermost wait behind it - as an open-source embedded iPaaS, ByteChef could power those syncs so your engineers stay on the core PM experience. | Q27: Headcount unknown | R27: Vamsi Kurama (CEO & Co-founder) | S27: =COUNTIF(Contacts!$A:$A,A27) -> 1
A28: Secoda | B28: secoda.co | C28: Canada | D28: Dev tools | F28: Data tools | G28: AI data search/catalog/lineage | H28: Series A $14M Craft 2023 (FinSMEs (https://www.finsmes.com/2023/09/secoda-raises-14m-in-series-a-funding.html)) | I28: ~19–22 (LeadIQ (https://leadiq.com/c/secoda/60d3333f47ed3badf9a78fdd)) | J28: Docs promise integrations "on the roadmap" (Airflow, S3, great_expectations), invite requests via Slack/email (docs (https://docs.secoda.co/integrations)) | K28: 2/2/2/2/0 | L28: 8 | M28: 2 | N28: Ivica | O28: Your docs promise Airflow, S3 and great_expectations connectors 'on the roadmap' and ask users to email requests - clear the whole queue. | P28: Your integrations docs promise Airflow, S3, and great_expectations connectors 'on the roadmap' and ask users to email in requests - a 20-person team could clear that whole queue by embedding an open-source connector platform instead of building each one. | R28: Etai Mizrahi (CEO) | S28: =COUNTIF(Contacts!$A:$A,A28) -> 1
A29: SigNoz | B29: signoz.io | C29: USA | D29: Dev tools | F29: Observability | G29: Open-source OTel-native observability | H29: Series A $20M Dec 2025 (CB Insights (https://www.cbinsights.com/company/signoz)) | I29: ~51 (CB Insights (https://www.cbinsights.com/company/signoz)) | J29: Discord alert-channel request open since Jan 2023 from a paying-user thread (#2154 (https://github.com/SigNoz/signoz/issues/2154)); 24 open integration issues | K29: 2/2/2/2/0 | L29: 8 | M29: 2 | N29: Ivica | O29: The Discord alert-channel request your own team filed from a paying-user thread has been open since January 2023. | P29: The Discord alert-channel request your own team filed from a user Slack thread has been open since January 2023 - open-source to open-source, ByteChef could give SigNoz every alert destination Datadog has without burning core engineering time. | R29: Pranay Prateek (Co-founder) | S29: =COUNTIF(Contacts!$A:$A,A29) -> 1
A30: Awell | B30: awellhealth.com | C30: Belgium | D30: EU vertical | F30: Health (clinical workflows) | G30: Developer platform for clinical workflows (CareOps) | H30: Seed $5M, Sep 2023 (Tech.eu (https://tech.eu/2023/09/19/awell-secures-5m-to-automate-clinician-workflows/)) | I30: unknown | J30: EHR connectivity hand-built extension by extension (developer hub (https://developers.awellhealth.com/awell-extensions/marketplace/athenahealth)); NOTE: partial conceptual overlap with ByteChef - scope pitch to EHR connector infra | K30: 2/1/2/2/1 | L30: 8 | M30: 2 | N30: Co-founder | O30: Each EHR integration is hand-built extension by extension - a self-serve connector catalog while your team stays on care flows. | P30: Your extensions marketplace shows each EHR integration built by hand - an embeddable integration engine could give Awell customers a self-serve connector catalog while your team stays focused on care flows. | Q30: Conceptual overlap with ByteChef - scope pitch to EHR connector infra | R30: Thomas Vande Casteele (Co-founder & CEO) | S30: =COUNTIF(Contacts!$A:$A,A30) -> 1
A31: Chainels | B31: getchainels.com | C31: Netherlands | D31: EU vertical | F31: Proptech (tenant experience) | G31: Tenant-experience app (400+ communities, 16 countries) | H31: Series A ~€3M, Jan 2023 (EuropaProperty (https://europaproperty.com/chainels-secures-e3-million-series-a-investment/)) | I31: unknown | J31: Syncs lease/billing/maintenance from each landlord's PMS/ERP; modest marketplace (Entrata, Lavanda, Yardi, Dynamics, HubSpot, Stripe) (marketplace (https://getchainels.com/marketplace/urbanos)) | K31: 2/1/2/2/1 | L31: 8 | M31: 2 | N31: Co-founder | O31: Every new landlord runs a PMS your Entrata/Yardi connectors do not cover - stop letting PMS hookups gate deals. | P31: Every new landlord you sign runs a different PMS than your Entrata/Yardi connectors cover - we give vertical SaaS teams an embedded integration layer so the long tail of PMS hookups stops gating deals. | Q31: Headcount unknown | R31: Erwin Buckers (Founder & CEO); Christiaan Titos Bolivar (Lead Developer - no formal CTO title exists) | S31: =COUNTIF(Contacts!$A:$A,A31) -> 2
A32: Dockflow | B32: dockflow.com | C32: Belgium | D32: EU vertical | F32: Logistics (maritime) | G32: Container-tracking platform for freight forwarders | H32: Seed €1.4M Dec 2025 (announcement (https://dockflow.com/29b-in-cargo-tracked-dockflow-raises-e1-4m-to-turn-maritime-data-into-predictive-ai/)) | I32: unknown (small) | J32: Sells on TMS/ERP/WMS hookups; connectors announced one at a time (Portbase) (post (https://dockflow.com/portbase-integration-freight-forwarders/)) | K32: 2/1/2/2/1 | L32: 8 | M32: 2 | N32: Co-founder | O32: Each new forwarder means another TMS/ERP hookup like your Portbase build - let customers self-serve those connections. | P32: Each new forwarder you onboard means another TMS/ERP hookup like your Portbase build - an embedded iPaaS would let your customers self-serve those connections instead of your engineers building each one. | Q32: Headcount unknown | R32: Pauline Van Ostaeyen (Co-Founder - commercial/leadership focus, no one holds literal "CEO" title); Michiel Valee (Co-Founder / Tech Lead) | S32: =COUNTIF(Contacts!$A:$A,A32) -> 2
A33: EverReal | B33: everreal.co | C33: Germany | D33: EU vertical | F33: Proptech (leasing/sales) | G33: White-label rental/sale transaction automation (175k+ units) | H33: Seed 7-figure HTGF 2019; later unknown (HTGF (https://www.htgf.de/en/everreal-successfully-completes-seed-investment-round/)) | I33: unknown | J33: GTM depends on ERP interfaces to housing systems (Wodis, DOMUS, iX-Haus); Aareon connection via third-party low-code tech (Partner-Schnittstellen (https://de.everreal.co/business/partner-schnittstellen)) | K33: 2/1/2/2/1 | L33: 8 | M33: 2 | N33: Co-founder | O33: The Wodis/DOMUS/iX-Haus interface list is the hardest part of every deal - reusable connectors your team configures, not codes. | P33: Your Wodis/DOMUS/iX-Haus interface list is the hardest part of every EverReal deal - an embedded open-source iPaaS turns those one-off ERP projects into reusable connectors your team configures, not codes. | Q33: Later funding rounds unknown | R33: Nessim Djerboua (CEO & Founder); Liviu Ignat (CTO & Co-Founder) | S33: =COUNTIF(Contacts!$A:$A,A33) -> 2
A34: FreightSuite | B34: freightsuite.com | C34: UK | D34: EU vertical | F34: Logistics (forwarding TMS) | G34: AI-native TMS positioned against CargoWise | H34: Pre-A $4.5M, Dec 2025 (The Loadstar (https://theloadstar.com/ls_press_release/freightsuite-secures-4-5m-pre-series-a-to-challenge-the-legacy-tms-market/)) | I34: unknown (small) | J34: Roadmap IS connector buildout: Freightos, Clearport, AEB, CrimsonLogic (Freightos PR (https://www.freightos.com/press-release/freightos-enables-live-air-cargo-booking-in-freightsuites-ai-native-tms/)) | K34: 2/1/2/2/1 | L34: 8 | M34: 2 | N34: Co-founder | O34: Out-integrating CargoWise needs dozens more connectors beyond Freightos and Clearport - a connector factory without diverting your AI roadmap. | P34: To out-integrate CargoWise you'll need dozens more connectors beyond Freightos and Clearport - an embedded open-source iPaaS gives you that connector factory without diverting your core AI roadmap. | Q34: Size unverified | R34: Samuel Moore (Co-Founder (CEO per third-party org chart)); - not confirmed - (William Jacobs is technical co-founder but no source confirms a CTO-equivalent title) | S34: =COUNTIF(Contacts!$A:$A,A34) -> 2
A35: Harbor Lab | B35: harborlab.com | C35: Greece | D35: EU vertical | F35: Logistics (maritime ops) | G35: Port-cost (DA) management for shipowners | H35: Series A €14.7M, May 2024 (EU-Startups (https://www.eu-startups.com/2024/05/greek-maritime-software-harbor-lab-raises-e14-7-million-to-streamline-port-cost-management/)) | I35: ~94–106 (Tracxn (https://tracxn.com/d/companies/harbor-lab/___3YX6sSp1IXiPlUPNMb8HGi0tkxFxqXnC1pFKUb5fC8)) | J35: ERP/accounting hookups required; advertises cloud-ERP integration but no public connector catalog (harborlab.com (https://www.harborlab.com/)) | K35: 2/2/1/2/1 | L35: 8 | M35: 2 | N35: Co-founder | O35: Every DA your platform approves lands in a shipowner's ERP - embedded white-label ERP connectors shipped in weeks. | P35: Every DA your platform approves ultimately lands in a shipowner's ERP - embedded, white-label ERP connectors (SAP, Navision, maritime accounting suites) are exactly what we let SaaS teams ship in weeks. | Q35: Generic pain signal only - verify on first call | R35: Antonis Malaxianakis (Founder & CEO); Spyros Lamprinidis (Chief Technology Officer) | S35: =COUNTIF(Contacts!$A:$A,A35) -> 2
A36: HERO Software | B36: hero-software.de | C36: Germany | D36: EU vertical | F36: Construction (trades) | G36: Cloud software for tradespeople DACH; 30k+ users | H36: Series B €40M, Jul 2024 (Tech.eu (https://tech.eu/2024/07/12/hero-software-secures-40m-series-b-for-tradespeople-saas-platform/)) | I36: 125+ (one source ~230) (about (https://hero-software.de/about-us)) | J36: Interface list bounded, partly export-based: DATEV export, Datanorm/IDS/UGL formats (Schnittstellen (https://hero-software.de/features/schnittstellen)) | K36: 2/1/2/2/1 | L36: 8 | M36: 2 | N36: Co-founder | O36: Your Schnittstellen page covers DATEV export and supplier data formats - each new country means new systems; solve it embedded. | P36: Your Schnittstellen page covers DATEV export and supplier data formats - as the DACH market leader expands across Europe, each new country means new accounting/supplier systems, precisely the connector problem we solve embedded in your product. | Q36: Possibly ~230 employees - verify | R36: Michael Kessler (Founder & CEO (Geschäftsführer)); Constantin Schomburg (Chief Technology Officer) | S36: =COUNTIF(Contacts!$A:$A,A36) -> 2
A37: Legl | B37: legl.com | C37: UK | D37: EU vertical | F37: Legal (law-firm ops) | G37: Payments, onboarding, AML/compliance for law firms | H37: Series B $18M, May 2022 (TechCrunch (https://techcrunch.com/2022/05/17/legl-series-b/)) | I37: unknown | J37: Only a handful of PMS connectors (Clio, Actionstep, Sharedo) vs dozens in market (integrations (https://legl.com/integrations)) | K37: 2/1/2/2/1 | L37: 8 | M37: 2 | N37: Co-founder | O37: Clio, Actionstep and Sharedo are built but most UK firms sit on other PMS - cover the long tail without a connector team. | P37: You've built Clio, Actionstep and Sharedo integrations, but most UK firms sit on other PMS - an embedded integration platform would let you cover the long tail without a connector team. | Q37: Headcount unknown | R37: Julia Salasky (CEO); Matt Jared (CTO) | S37: =COUNTIF(Contacts!$A:$A,A37) -> 2
A38: Rentio | B38: rentio.be | C38: Belgium | D38: EU vertical | F38: Proptech (rental mgmt) | G38: Rental management + payments for Belgian landlords/agencies | H38: Seed €1.3M Baloise 2020 (Baloise (https://www.baloise.com/en/home/news-stories/news/media-releases/2020/baloise-insurance-invests-in-digital-rental-process-of-rentio.html)) | I38: unknown (small) | J38: Accounting via third-party invoicing bridge EenvoudigFactureren rather than native (help doc (https://help.eenvoudigfactureren.be/support/solutions/articles/101000479768-rentio-de-totaaloplossing-voor-ver-huur)) | K38: 2/1/2/2/1 | L38: 8 | M38: 2 | N38: Co-founder | O38: Accounting sync routes through EenvoudigFactureren today - own native Exact/Winbooks/bank connections in-product. | P38: You route accounting sync through EenvoudigFactureren today - an embedded iPaaS would let Rentio own native Exact/Winbooks/bank connections in-product, without an integrations hire. | Q38: Stale seed round; size unknown - confirm company activity | R38: Stijn Roels (CEO (LinkedIn shows "Co-Founder")); - not confirmed - (No source titles anyone CTO; Dries Van Schevensteen is Lead Engineer/Developer) | S38: =COUNTIF(Contacts!$A:$A,A38) -> 2
A39: Carv | B39: carv.com | C39: Netherlands | D39: HR/fin-ops | F39: Recruiting AI | G39: Agentic AI for volume hiring that writes back into the ATS | H39: Seed $10M, Jun 2024 (PR Newswire (https://www.prnewswire.com/news-releases/amsterdam-based-carv-raises-10m-to-offload-admin-from-recruiters-and-realize-recruiter-ai-synergy-302162038.html)) | I39: unknown (seed scale) | J39: Product depends on per-ATS integrations; public list short (Bullhorn, Workable, Recruitee, Carerix, Lexo) vs. hundreds of ATSes (Bullhorn page (https://www.carv.com/integrations/bullhorn), ATS guide (https://www.carv.com/guides/guide-ai-and-the-ats-three-setups-for-seamless-recruitment-process)) | L39: 8 | M39: 2 | N39: Ivica | O39: Carv's value lands only when data flows back into the customer's ATS and you support a handful today - get Bullhorn plus the long tail. | P39: Carv's value lands only when structured data flows back into the customer's ATS, and you support a handful today - an embedded iPaaS gets you Bullhorn-plus-the-long-tail without an integrations backlog blocking sales. | R39: Barend Raaff (Co-Founder - no one holds explicit "CEO" title; prior CEO experience at Harver); Steven Kroon (Chief Technology Officer) | S39: =COUNTIF(Contacts!$A:$A,A39) -> 2
A40: Circula | B40: circula.com | C40: Germany | D40: HR/fin-ops | F40: Expense / spend | G40: Expense management, benefits and cards with deep DATEV focus | H40: Series A €12M (2022) + €15M ext (May 2025) (EU-Startups (https://www.eu-startups.com/2025/05/german-fintech-startup-circula-secures-e15-million-as-it-cuts-expense-admin-by-80/)) | I40: ~100–150 emp (EU-Startups 2022 (https://www.eu-startups.com/2022/01/berlin-based-employee-finance-app-circula-scores-e12-million-and-plans-international-expansion/)) | J40: Integration rated weak spot at 8.2 on G2, reviewers citing "more manual entry and potential errors" (Research.com (https://research.com/software/reviews/circula), G2 (https://www.g2.com/products/circula/reviews)) | L40: 8 | M40: 2 | N40: Ivica | O40: G2 scores integrations as your weakest dimension with manual re-entry complaints - extend DATEV-grade depth to every payroll and HR system. | P40: Circula wins on DATEV depth, but G2 scores integrations as your weakest dimension with reviewers citing manual re-entry - an embedded integration layer would extend that DATEV-grade experience to every payroll and HR system your customers run. | Q40: Weaker pain evidence | R40: Nikolai Skatchkov (CEO & Co-Founder); Roman Leicht (CTO & Co-Founder) | S40: =COUNTIF(Contacts!$A:$A,A40) -> 2
A41: Embat | B41: embat.io | C41: Spain | D41: HR/fin-ops | F41: Treasury / fin-ops | G41: Real-time treasury management connecting banks and ERPs | H41: Series A €14.7M (Feb 2024), Series B €30M (May 2026) (EU-Startups (https://www.eu-startups.com/2024/02/madrid-based-fintech-embat-raises-e14-7-million-series-a-to-fuel-up-next-gen-treasury-management/), FinSMEs (https://www.finsmes.com/2026/05/embat-raises-eur30m-in-series-b-funding.html)) | I41: unknown (~Series B scale) | J41: Runs an "ERP Connectivity" department; hiring "ERP (Business Central / Dynamics F&O) Connectivity Specialist" + ERP Product Owner + ERP Partnerships Manager (The Org (https://theorg.com/org/embat/teams/erp-connectivity), Glassdoor (https://www.glassdoor.com/Jobs/Embat-Madrid-Spain-Jobs-EI_IE8376796.0,5_IL.6,18_IC2664239.htm)) | L41: 8 | M41: 2 | N41: Ivica | O41: You are hiring ERP Connectivity Specialists per ERP flavor - the clearest sign the connector backlog is outgrowing the team. | P41: You're hiring ERP Connectivity Specialists per ERP flavor - Business Central, F&O, SAP - the clearest sign the connector backlog is outgrowing the team; that's the exact problem we let you embed away. | Q41: Fresh Series B; near size ceiling | R41: Antonio Berga (Co-CEO & Founder (Carlos Serrano García-Lisón is the other Co-CEO, no LinkedIn found)); Tomás Gil (CTO) | S41: =COUNTIF(Contacts!$A:$A,A41) -> 2
A42: Kolleno | B42: kolleno.com | C42: UK | D42: HR/fin-ops | F42: AR / collections | G42: AI accounts-receivable and payments automation for SMEs | H42: Seed £4M, Mar 2022 (FinSMEs (https://www.finsmes.com/2022/03/kolleno-raises-4m-in-seed-funding.html)) | I42: unknown (seed scale) | J42: Product depends on ERP/CRM sync but named connector list short (NetSuite, Dynamics BC, Salesforce, SAP S/4HANA) (LeadIQ (https://leadiq.com/c/kolleno/5f7cdcc312990524e7bd8e37)); integrations page not verifiable (403) | L42: 8 | M42: 2 | N42: Ivica | O42: Your pitch is 'keeping everything in sync' yet the public connector list covers four ERPs - match Sidetrade-level breadth at seed size. | P42: Kolleno's pitch is 'keeping everything in sync - data, systems, people', yet the public connector list covers four ERPs; embedding an open-source iPaaS would let a seed-stage team match Sidetrade-level integration breadth. | Q42: Integrations page 403 during research | R42: Dimitri Raziev (CEO & Co-Founder); Ron Danenberg (CTO & Founder) | S42: =COUNTIF(Contacts!$A:$A,A42) -> 2
A43: Omnea | B43: omnea.co | C43: UK | D43: HR/fin-ops | F43: Procurement | G43: Procurement orchestration & supplier risk for mid-market/enterprise | H43: Series A $20–25M (Oct 2024, Accel); $50M follow-on Sep 2025 (TechCrunch (https://techcrunch.com/2024/10/14/omnea-raises-25m-to-tackle-the-painfully-annoying-procurement-market/), PR Newswire (https://www.prnewswire.com/news-releases/omnea-raises-50m-to-make-procurement-every-cfos-competitive-advantage-302559153.html)) | I43: ~150–170 emp (Tracxn (https://tracxn.com/d/companies/omnea/__IK_t21BAokKxT_Xn6RRwSeTmPqUzp6IYRtfnC9CcEtE)) | J43: Hiring "Integration Solutions Engineer" (£65–95k, London) to "troubleshoot complex integration challenges" (Built In (https://builtin.com/job/integration-solutions-engineer/4797736)) | L43: 8 | M43: 2 | N43: Ivica | O43: You are hiring an Integration Solutions Engineer to untangle customer integration challenges - turn bespoke hookups into a self-serve connector catalog. | P43: Omnea is hiring an Integration Solutions Engineer to untangle customer integration challenges - an embedded iPaaS would turn those bespoke ERP/SSO hookups into a self-serve connector catalog your CS team can drive. | Q43: 150-170 employees; near size ceiling | R43: Ben Freeman (Co-Founder & CEO); Ben Allen (Co-Founder & CTO) | S43: =COUNTIF(Contacts!$A:$A,A43) -> 2
A44: Quandri | B44: quandri.io | C44: Canada | D44: HR/fin-ops | F44: Insurance ops | G44: AI renewal-intelligence platform for insurance agencies/brokerages | H44: Series A $8.5M (2023) + US$12M (Jul 2025) (newsroom (https://www.quandri.io/newsroom/series-a-funding-transform-insurance-process-automation), BusinessWire (https://www.businesswire.com/news/home/20250716833650/en/Quandri-Raises-US$12M-to-Scale-AI-Automation-for-Insurance-Agencies-Across-North-America)) | I44: unknown (Series A scale) | J44: Growth gated on AMS connectors, each a press release: certified Applied Epic, then Vertafore AMS360 + HawkSoft Apr 2026 (BusinessWire (https://www.businesswire.com/news/home/20260407446762/en/Quandri-Expands-Integration-Ecosystem-with-Vertafore-AMS360-and-HawkSoft-Broadening-Access-to-Renewal-Intelligence), newsroom (https://www.quandri.io/newsroom/quandri-announces-certified-integration-applied-epic)) | L44: 8 | M44: 2 | N44: Ivica | O44: Every AMS integration (Epic, AMS360, HawkSoft) is a months-long project and a press release - cover the AMS long tail in one quarter. | P44: Every new agency-management-system integration - Epic, AMS360, HawkSoft - is currently a months-long project and a press release; embedding an integration platform would let you cover the AMS long tail in one quarter. | R44: Jackson Fregeau (Co-Founder & CEO); Heather Natour (VP of Engineering - no one holds CTO title) | S44: =COUNTIF(Contacts!$A:$A,A44) -> 2
A45: Solvimon | B45: solvimon.com | C45: Netherlands | D45: HR/fin-ops | F45: Billing / monetization | G45: Usage-based billing platform by ex-Adyen billing leads | H45: Seed €9M, Nov 2023 (Northzone) (Tech.eu (https://tech.eu/2023/11/13/northzone-backs-solvimon-with-eur9-million-for-advanced-billing-solutions/)) | I45: unknown (seed scale) | J45: Public accounting connectors limited to a handful (NetSuite, Xero, QuickBooks, Exact) - thin vs. billing category norms (integrations (https://www.solvimon.com/integrations)); full page not verifiable (403) | L45: 8 | M45: 2 | N45: Ivica | O45: Four accounting connectors listed while enterprise billing deals hinge on the buyer's exact ERP - answer 'do you integrate with X?' with yes. | P45: Solvimon lists four accounting connectors today while enterprise billing deals routinely hinge on the customer's exact ERP - an embedded integration layer would let a seed-stage team credibly answer 'do you integrate with X?' with yes. | Q45: Integrations page 403 during research | R45: Kim Verkooij (Co-Founder & CEO); Etienne Gerts (Co-Founder & CTO) | S45: =COUNTIF(Contacts!$A:$A,A45) -> 2
A46: Younium | B46: younium.com | C46: Sweden | D46: HR/fin-ops | F46: Subscription billing | G46: B2B subscription management & billing for Nordic/EU SaaS | H46: ~€2.76M Mar 2024; ~$12M total (EU-Startups (https://www.eu-startups.com/2024/03/stockholm-based-younium-secures-e2-7-million-to-solidify-subscription-management-across-europe/), Tracxn (https://tracxn.com/d/companies/younium/__Zvhv9NG1DeYTzePvzSAgC3XtGcXPEJHKyKF-GV3Z7BA)) | I46: unknown (51–200 band per Tracxn) | J46: G2 reviewer: "horrible when it comes to Salesforce integration"; rigid payment setup (The CFO Club (https://thecfoclub.com/tools/younium-review/), G2 (https://www.g2.com/products/younium/reviews)) | L46: 8 | M46: 2 | N46: Ivica | O46: A G2 reviewer called your Salesforce integration 'horrible' - rebuild CRM/ERP sync once and expose every connector mid-market buyers expect. | P46: A G2 reviewer called your Salesforce integration 'horrible' - painful to read, but fixable: an embedded integration platform would let you rebuild CRM/ERP sync once and expose every other connector your mid-market buyers expect. | Q46: Funding picture murky; treat stage as small Series A | R46: Niclas Lilja (Founder & CEO) | S46: =COUNTIF(Contacts!$A:$A,A46) -> 1
A47: AgVend | B47: agvend.com | C47: USA | D47: US vertical | F47: Agriculture - ag retail | G47: White-labeled digital grower portals for ag retailers | H47: Series B, $62.4M total (Tracxn (https://tracxn.com/d/companies/agvend/__gB1NIy7MYN1NMw3_XZqIe2pVcxCmU9ORpkhrs9lsuGQ)) | J47: Platform defined by its "Integration Ecosystem" - every retailer onboarding needs ERP sync (agvend.com (https://www.agvend.com/)) | L47: 8 | M47: 2 | N47: Co-founder | O47: Your grower portals live or die by ERP, agronomy and grain-system syncs - onboard the next ag ERP without a bespoke build. | P47: AgVend's grower portals live or die by ERP, agronomy, and grain-system syncs - an embedded iPaaS would let you onboard the next ag ERP without a bespoke build every time. | Q47: Round label sourced via Tracxn only | R47: Alexander Reichert (Co-Founder & CEO); Eli Rosenberg (Co-Founder & CPO) | S47: =COUNTIF(Contacts!$A:$A,A47) -> 2
A48: Archy | B48: archy.com | C48: USA | D48: US vertical | F48: Health - dental | G48: Cloud-native dental practice management | H48: Series A $15M ($27M total), Oct 2024 (PR Newswire (https://www.prnewswire.com/news-releases/archy-raises-15-million-series-a-round-to-transform-dental-practices-with-automated-cloud-based-platform-underpinned-by-ai-302286180.html)) | J48: Bridges hardware/software zoo - Schick native, rest via TWAIN (sensors (https://www.archy.com/sensors)); G2 notes integration friction (G2 (https://www.g2.com/products/archy/reviews)) | L48: 8 | M48: 2 | N48: Co-founder | O48: Sensors, imaging AI and payer systems each still need a bespoke connector - ship them natively instead of one TWAIN driver at a time. | P48: Archy's pitch is replacing clunky dental-software bridges, yet sensors, imaging AI, and payer systems each still need a bespoke connector - ByteChef lets your team ship those natively instead of one TWAIN driver at a time. | R48: Jonathan Rat (Co-Founder & CEO) | S48: =COUNTIF(Contacts!$A:$A,A48) -> 1
A49: Carepatron | B49: carepatron.com | C49: New Zealand | D49: US vertical | F49: Health - practice mgmt | G49: All-in-one practice management for health/wellness practitioners | H49: Seed ~$5M, Nov 2023 (TechCrunch (https://techcrunch.com/2023/11/03/carepatron/)) | J49: Capterra: no Medicare integration, no insurance billing, financial-reporting gaps - users requesting integrations (Capterra (https://www.capterra.com/p/195467/Care-Patron/)) | L49: 8 | M49: 2 | N49: Co-founder | O49: Capterra reviewers keep asking for Medicare, insurance-billing and accounting integrations - embedded white-label connectors instead of hand-builds. | P49: Capterra reviewers love Carepatron but keep asking for Medicare, insurance-billing, and accounting integrations - we power embedded, white-label connectors so your team doesn't hand-build each one. | R49: Jamie Frew (Co-Founder) | S49: =COUNTIF(Contacts!$A:$A,A49) -> 1
A50: Hona | B50: hona.com | C50: USA | D50: US vertical | F50: Legal - client comms | G50: Client-communication portal for consumer law firms (YC) | H50: Series A $9.5M, Jun 2024 (Law.com (https://www.law.com/legaltechnews/2024/06/17/case-tracking-startup-hona-announces-9-5m-series-a-investment/)) | J50: Depends on case-management sync; page covers a handful of PMSs (Clio, Filevine, Smokeball…) (integrations (https://www.hona.com/integrations)) | L50: 8 | M50: 2 | N50: Co-founder | O50: Your edge is deep case-management sync with Clio, Filevine and Smokeball - cover the next ten PMSs prospects ask about. | P50: Hona's edge is deep case-management sync with Clio, Filevine, and Smokeball - ByteChef would let you cover the next ten PMSs prospects ask about without growing the integrations team. | R50: Matt McClellan (Co-Founder); Joshua Christensen (Co-Founder & CTO) | S50: =COUNTIF(Contacts!$A:$A,A50) -> 2
A51: Milk Moovement | B51: milkmoovement.com | C51: Canada | D51: US vertical | F51: Agriculture - dairy | G51: Supply-chain visibility for dairy co-ops/producers/processors | H51: Series A $20M, Jun 2022 (PR Newswire (https://www.prnewswire.com/news-releases/milk-moovement-raises-20-million-usd-to-transform-the-dairy-industrys-supply-chain-301583386.html)) | J51: Lab results accepted "through API, FTP, or email"; touts legacy-system integrations (Quality & Labs (https://www.milkmoovement.com/products/quality-and-labs)) | L51: 8 | M51: 2 | N51: Co-founder | O51: You ingest lab results 'via API, FTP, or email' - turn that legacy glue into productized white-label integrations co-ops configure themselves. | P51: You already ingest lab results 'via API, FTP, or email' - ByteChef turns exactly that kind of legacy glue into productized, white-label integrations your co-op customers configure themselves. | R51: Jon King (Co-Founder & CEO); Christopher O'Malley (CTO) | S51: =COUNTIF(Contacts!$A:$A,A51) -> 2
A52: RentCheck | B52: getrentcheck.com | C52: USA | D52: US vertical | F52: Proptech - inspections | G52: Resident-led property inspection automation | H52: Seed $2.6M ($3.6M total), Aug 2021 (TechCrunch (https://techcrunch.com/2021/08/09/rentcheck-raises-millions/)) | J52: "Buildium integration coming soon" + thin partner set (AppFolio, Rent Manager, Zapier, Latchel) (AppFolio partner page (https://www.appfolio.com/partners/rentcheck)); from search snippets | L52: 8 | M52: 2 | N52: Co-founder | O52: Buildium sits at 'coming soon' on your integrations lineup - ship Buildium, Propertyware and the PM long tail in weeks. | P52: Saw Buildium sitting at 'coming soon' on your integrations lineup - ByteChef lets a team your size ship Buildium, Propertyware, and the rest of the PM long tail in weeks, white-labeled. | Q52: Signal from search snippets; may be too small to buy | R52: Marco Nelson (Founder & CEO); Matias Pan (Head of Engineering) | S52: =COUNTIF(Contacts!$A:$A,A52) -> 2
A53: Siteline | B53: siteline.com | C53: USA | D53: US vertical | F53: Construction - billing | G53: A/R and pay-app billing for trade contractors | H53: Series A $15M ($18.4M total), Feb 2022 (blog (https://www.siteline.com/blog/siteline-announces-series-a-funding)) | J53: Maintains bidirectional syncs with 8+ construction ERPs in-house (integrations (https://www.siteline.com/integrations) via search - 403; Foundation partner page (https://www.foundationsoft.com/partner/siteline/)) | L53: 8 | M53: 2 | N53: Co-founder | O53: You maintain bidirectional syncs to eight-plus construction ERPs in-house - offload connector maintenance and keep engineers on billing workflows. | P53: You maintain bidirectional syncs to Sage, Vista, Foundation, Acumatica, and QuickBooks in-house - ByteChef offloads that connector maintenance so your engineers stay on billing workflows, not ERP plumbing. | Q53: Integrations page 403 during research | R53: Claire Wilson (Co-Founder & CEO); Gloria Lin (Co-Founder & CPO) | S53: =COUNTIF(Contacts!$A:$A,A53) -> 2
A54: VXT | B54: vxt.co.nz | C54: New Zealand | D54: US vertical | F54: Legal - communications | G54: VoIP for law firms, auto-logs calls/time into PMSs | H54: Pre-A NZ$1.8M, Mar 2024 (Startup Daily (https://www.startupdaily.net/topic/funding/kiwi-legal-tech-startup-vxt-banks-1-65-million-in-pre-series-a/)) | J54: Value prop IS PMS integrations (Clio, MyCase, LEAP, Smokeball, PracticeEvolve, Actionstep), shipped one at a time (Clio announcement (https://www.vxt.co.nz/post/vxt-clio-integration-announcement)) | L54: 8 | M54: 2 | N54: Co-founder | O54: You ship practice-management integrations one announcement at a time - cover the PMS long tail all at once. | P54: You've been shipping practice-management integrations one announcement at a time - most recently Clio - an embedded integration platform would let VXT cover the PMS long tail all at once. | R54: Lucy Turner (Co-Founder & CTO) | S54: =COUNTIF(Contacts!$A:$A,A54) -> 1
A55: Dash0 | B55: dash0.com | C55: Germany/USA | D55: Dev tools | F55: Observability | G55: AI-native OTel observability (Instana founder) | H55: Series A $35M Oct 2025 (blog (https://www.dash0.com/blog/dash0-raises-usd35-million-series-a)) | I55: unknown | J55: 103 integrations almost all ingestion (hub (https://www.dash0.com/hub/integrations)); outbound alerting = PagerDuty + bare Slack webhook (docs (https://www.dash0.com/docs/integrations/int_alerting_pagerduty/overview)) | K55: 2/1/1/2/1 | L55: 7 | M55: 3 | N55: Ivica | O55: 103 ingestion integrations but alerts only reach PagerDuty and a bare Slack webhook - Datadog-grade outbound reach in one quarter. | P55: Dash0 lists 103 ingestion integrations but alerts still only reach PagerDuty and a bare Slack webhook - an embedded open-source iPaaS could give your young platform Datadog-grade outbound reach (Jira, ServiceNow, Opsgenie, Teams) in one quarter. | Q55: EU status ambiguous; inferred pain | R55: Mirko Novakovic (CEO); Ben Blackmore (CTO) | S55: =COUNTIF(Contacts!$A:$A,A55) -> 2
A56: Formbricks | B56: formbricks.com | C56: Germany | D56: Dev tools | F56: Surveys | G56: Open-source in-app surveys (Qualtrics alt) | H56: Pre-seed OSS Capital (Crunchbase (https://www.crunchbase.com/organization/formbricks)) | I56: unknown (small) | J56: Requests for Telegram - explicitly to avoid "complex third-party tools like Zapier, Make.com" (#7506 (https://github.com/formbricks/formbricks/issues/7506)) - and Snowflake (#7109 (https://github.com/formbricks/formbricks/issues/7109)) | K56: 1/1/2/2/1 | L56: 7 | M56: 3 | N56: Ivica | O56: Your users file Telegram and Snowflake requests specifically to stop paying for Zapier - power those destinations inside Formbricks. | P56: Your users are filing requests for Telegram and Snowflake integrations specifically so they can stop paying for Zapier - as a fellow German open-source company, we could power those destinations inside Formbricks with an embedded AGPL-friendly iPaaS. | Q56: Small team - may be below buying size | R56: Johannes Dancker (Founder & CEO (tentative)); Matti Nannt (Founder & CTO) | S56: =COUNTIF(Contacts!$A:$A,A56) -> 2
A57: kapa.ai | B57: kapa.ai | C57: Denmark | D57: Dev tools | F57: Dev tools / AI support | G57: AI assistants answering from product docs | H57: Seed $3.2M Oct 2024 (blog (https://www.kapa.ai/blog/kapa-ai-secures-3-2m-to-advance-technical-ai-assistants)) | I57: unknown; 16 open roles | J57: Value proportional to connectors: 30+ sources + Slack/Discord/Zendesk surfaces (kapa.ai (https://www.kapa.ai/)) - inferred | K57: 2/1/1/2/1 | L57: 7 | M57: 3 | N57: Ivica | O57: Your pitch depends on 30+ doc sources plus Slack, Discord and Zendesk surfaces - every enterprise deal adds another connector ask. | P57: kapa's pitch depends on connecting 30+ doc sources plus Slack, Discord, and Zendesk surfaces - every new enterprise deal adds another connector ask, and an embedded open-source iPaaS would let your seed-stage team say yes to all of them. | Q57: Inferred pain | R57: Emil Sorensen (CEO); Finn Bauer (Co-Founder) | S57: =COUNTIF(Contacts!$A:$A,A57) -> 2
A58: Lightdash | B58: lightdash.com | C58: UK | D58: Dev tools | F58: Data tools / BI | G58: Open-source BI for dbt | H58: Series A $11M Accel Oct 2024 (FinSMEs (https://www.finsmes.com/2024/10/lightdash-raises-11m-in-series-a-funding.html)) | I58: unknown | J58: StarRocks connector open since Nov 2023 (#7940 (https://github.com/lightdash/lightdash/issues/7940)); 9 open integration issues | K58: 2/1/2/1/1 | L58: 7 | M58: 3 | N58: Ivica | O58: The StarRocks connector request has been open since 2023 - keep the Accel funding on the AI analyst, not connector plumbing. | P58: The StarRocks connector request has been open on your repo since 2023 - open-source to open-source, ByteChef could handle warehouse and delivery integrations so your Accel funding goes to the AI analyst, not connector plumbing. | Q58: Headcount unknown | R58: Hamzah Chaudhary (Co-Founder & CEO); Oliver Laslett (Co-Founder & CTO) | S58: =COUNTIF(Contacts!$A:$A,A58) -> 2
A59: Sifflet | B59: siffletdata.com | C59: France | D59: Dev tools | F59: Data observability | G59: Full-stack data observability/quality | H59: Series A €12.8M (2023) + €16M (Jun 2025) (The SaaS News (https://www.thesaasnews.com/news/sifflet-raises-12-million-in-series-a)) | I59: unknown | J59: Catalog ~9 data platforms + dbt/Fivetran/Airflow (integrations (https://www.siffletdata.com/product/integrations)) - thin vs Monte Carlo-class | K59: 2/1/1/2/1 | L59: 7 | M59: 3 | N59: Ivica | O59: Data-observability deals are won on connector coverage and your public catalog lists around ten platforms - triple the surface, not the team. | P59: Data observability deals are won on connector coverage, and Sifflet's public catalog lists around ten platforms - embedding an open-source integration engine could triple that surface without tripling your Paris engineering team. | Q59: Headcount unknown | R59: Salma Bakouk (CEO & Co-founder) | S59: =COUNTIF(Contacts!$A:$A,A59) -> 1
A60: Contractbook | B60: contractbook.com | C60: Denmark | D60: EU vertical | F60: Legal (CLM) | G60: Contract automation for SMBs | H60: Series B $30M, Nov 2021 (Legal IT Insider (https://legaltechnology.com/clm-contractbook-raises-30m-series-b/)) | I60: unknown | J60: Zapier-first integration strategy ("9,000 apps on Zapier") = thin native layer (Zapier (https://zapier.com/apps/contractbook/integrations)) | K60: 2/1/2/1/1 | L60: 7 | M60: 3 | N60: Co-founder | O60: Your integration story largely runs through Zapier - native white-label CRM/ERP sync that Zapier cannot match on depth or data control. | P60: Contractbook's integration story today largely runs through Zapier - embedding an open-source integration platform would give your customers native, white-label CRM/ERP sync that Zapier can't match on depth or data control. | Q60: Headcount unknown | R60: Jarek Owczarek (Founder) | S60: =COUNTIF(Contacts!$A:$A,A60) -> 1
A61: Juro | B61: juro.com | C61: UK | D61: EU vertical | F61: Legal (CLM) | G61: Browser-native contract automation (6,000+ companies) | H61: Series B $23M, Jan 2022 (TechCrunch (https://techcrunch.com/2022/01/17/juro-series-b/)) | I61: ~60→130 plan (TechCrunch (https://techcrunch.com/2022/01/17/juro-series-b/)) | J61: CRM integration "a bit buggy"; deeper Salesforce/HubSpot/Workday connectors paywalled (Signeasy roundup (https://signeasy.com/blog/business/juro-reviews)) | K61: 2/2/1/1/1 | L61: 7 | M61: 3 | N61: Co-founder | O61: Users call the CRM integration buggy and deeper connectors sit behind add-on pricing - make integrations a strength instead of an upsell friction. | P61: Users praise Juro but call the CRM integration buggy and note deeper connectors sit behind add-on pricing - an embedded iPaaS could make robust integrations a product strength instead of an upsell friction point. | R61: Richard Mabey (Co-Founder & CEO) | S61: =COUNTIF(Contacts!$A:$A,A61) -> 1
A62: Lexroom.ai | B62: lexroom.ai | C62: Italy | D62: EU vertical | F62: Legal (AI research) | G62: GenAI legal research/drafting for civil-law firms (600+ clients) | H62: Series A €16.2M Sep 2025, Series B €42.9M May 2026 (EU-Startups (https://www.eu-startups.com/2026/05/italian-ai-legaltech-startup-lexroom-raises-e42-9-million-series-b-eight-months-after-e16-2-million-series-a/)) | I62: unknown | J62: Thin public surface (uploads + SSO); third-party flags missing PMS/DMS APIs (FAQ (https://www.lexroom.ai/en/faq), Beatable (https://beatable.co/analysis/4F469B52B8) - weak authority) | K62: 2/1/1/2/1 | L62: 7 | M62: 3 | N62: Co-founder | O62: Every firm will ask for their PMS and DMS to feed your AI - deliver that connector catalog without slowing the model roadmap. | P62: As Lexroom expands across civil-law Europe, every firm will ask for their PMS and DMS to feed your AI - an embedded integration platform delivers that connector catalog without slowing your model roadmap. | Q62: Weak-authority pain source; fresh large Series B | R62: Paolo Fois (Co-Founder & CEO) | S62: =COUNTIF(Contacts!$A:$A,A62) -> 1
A63: Light | B63: light.inc | C63: Denmark | D63: HR/fin-ops | F63: Accounting / ERP | G63: AI-native ERP/general ledger for multinational scale-ups | H63: Series A $30M, Sep 2025 (Balderton) (CNBC (https://www.cnbc.com/2025/09/25/ai-finance-startup-light-raises-funding-from-revolut-backer-balderton.html)) | I63: unknown (eng team "to triple by mid-2026", FinTech Futures (https://www.fintechfutures.com/venture-capital-funding/ai-accounting-start-up-light-targets-us-expansion-with-30m-series-a)) | J63: Chose to partner with Atlar for bank connectivity rather than build - connector buildout off-strategy; as a NetSuite replacement must match ERP-ecosystem breadth (partnership (https://www.atlar.com/blog/light-and-atlar-partner-to-create-the-first-end-to-end-ai-native-finance-stack), vs NetSuite (https://light.inc/versus/netsuite)) | L63: 7 | M63: 3 | N63: Ivica | O63: You outsourced bank connectivity to Atlar rather than build it - the same buy-not-build logic applies to the integrations a NetSuite challenger needs. | P63: You already outsourced bank connectivity to Atlar rather than build it - the same buy-not-build logic applies to the hundreds of business-tool integrations a NetSuite challenger needs, and that's exactly what an embedded OSS iPaaS provides. | Q63: Inferred pain | R63: Jonathan Sanders (CEO) | S63: =COUNTIF(Contacts!$A:$A,A63) -> 1
A64: Numeric | B64: numeric.io | C64: USA | D64: HR/fin-ops | F64: Accounting close | G64: AI-powered month-end close and accounting automation | H64: Series A $28M (Oct 2024), Series B $51M (Nov 2025) (TechCrunch (https://techcrunch.com/2024/10/10/numeric-grabs-28m-series-a-for-automating-accounting-with-ai/), StartupHub.ai (https://www.startuphub.ai/startups/numeric)) | I64: ~83–117 emp (PitchBook (https://pitchbook.com/profiles/company/470657-80)) | J64: GL connectors limited to NetSuite, QBO, Xero, Sage Intacct; no QuickBooks Enterprise - named gap (CurateSuite (https://curatesuite.com/accounting/tools/numeric)) | L64: 7 | M64: 3 | N64: Ivica | O64: Your close automation reaches four GLs and QuickBooks Enterprise is a named gap - chase FloQast's ERP coverage without diverting AI engineers. | P64: Numeric's close automation only reaches four GLs today and reviewers name QuickBooks Enterprise as a hard gap - an embedded integration platform would let you chase FloQast's ERP coverage without diverting AI engineers to connectors. | R64: Parker Gilbert (Co-Founder & CEO); Andrew Bihl (Co-Founder & CTO) | S64: =COUNTIF(Contacts!$A:$A,A64) -> 2
A65: Pivot | B65: pivotapp.ai | C65: France | D65: HR/fin-ops | F65: Procurement / AP | G65: AI source-to-pay platform for scale-ups and enterprises | H65: Series B €34.4M (May 2026); €60M total (EU-Startups (https://www.eu-startups.com/2026/05/paris-pivot-pockets-e34-4-million-to-power-enterprise-procurement-with-agentic-ai/)) | I65: ~95–104 emp (PitchBook (https://pitchbook.com/profiles/company/537348-16), Latka (https://getlatka.com/companies/pivot-app)) | J65: Native ERP integrations limited to NetSuite, SAP S/4HANA, Workday; rest pushed to an open API customers must build against (integrations (https://www.pivotapp.ai/integrations)) | L65: 7 | M65: 3 | N65: Ivica | O65: Three native ERP integrations and an open API for the rest - productize the build-it-yourself tail as you push into 25+ countries. | P65: Pivot ships three native ERP integrations and an open API for the rest - as you push into 25+ countries, an embedded iPaaS would turn that 'build it yourself' tail into productized connectors your enterprise buyers can switch on. | Q65: Weaker pain evidence; fresh Series B | R65: Romain Libeau (Co-Founder) | S65: =COUNTIF(Contacts!$A:$A,A65) -> 1
A66: Upflow | B66: upflow.io | C66: France | D66: HR/fin-ops | F66: AR / collections | G66: Accounts-receivable collection and payment platform | H66: Series A $15M (2021) + $5M (Apr 2024, YC/Lorimer) (FinSMEs (https://www.finsmes.com/2021/06/upflow-raises-15m-in-series-a-funding.html), Tracxn (https://tracxn.com/d/companies/upflow/__X0otRP4QUpn4jYATFOn_7c0VzkQ6Ye_ovmZ5esICM7Y)) | I66: unknown (Series A scale) | J66: Native connector set small (~NetSuite, QBO, Xero, Sage Intacct, Rillet + CRM); reviewers with complex models report "synchronization depends on manual tasks" (Research.com (https://research.com/software/reviews/upflow-review), support hub (https://support.upflow.io/hc/en-us/categories/13815951388945-Integrations)) | L66: 7 | M66: 3 | N66: Ivica | O66: Your half-dozen native ERP connectors are well-loved, but complex stacks still fall back to manual syncs - cover the billing-tool long tail. | P66: Upflow's half-dozen native ERP connectors are well-loved, but reviewers with complex stacks still fall back to manual syncs - an embedded integration layer would cover the billing-tool long tail without growing your core team. | Q66: Weaker pain evidence | R66: Alexandre Louisy (Co-Founder & CEO) | S66: =COUNTIF(Contacts!$A:$A,A66) -> 1
A67: AgriWebb | B67: agriwebb.com | C67: Australia | D67: US vertical | F67: Agriculture - livestock | G67: Livestock management for ranchers (AU/US/UK) | H67: Series B AU$40M ($64.6M total) (Business News Australia (https://www.businessnewsaustralia.com/articles/livestock-management-platform-agriwebb-closes-series-b-funding-round-at--40-million.html)) | J67: Marketplace promises "growing number" of systems; pushes partners to GraphQL API to self-integrate (Marketplace help (https://help.agriwebb.com/en/articles/6976821-agriwebb-marketplace-integrations)) | L67: 7 | M67: 3 | N67: Co-founder | O67: Your Marketplace promises a 'growing number' of connected farm systems - grow that number tenfold without a partner-engineering backlog. | P67: Your Marketplace promises a 'growing number' of connected farm systems - ByteChef is how vertical SaaS teams grow that number tenfold without a partner-engineering backlog. | Q67: Headcount unknown | R67: Kevin Baum (CEO & Co-Founder) | S67: =COUNTIF(Contacts!$A:$A,A67) -> 1
A68: Alvys | B68: alvys.com | C68: USA | D68: US vertical | F68: Logistics - TMS | G68: AI-powered cloud TMS for carriers/brokers | H68: Series B $40M ($77M total), 2025 (FreightWaves (https://www.freightwaves.com/news/alvys-40m-series-b-streamlining-freight-operations)) | J68: Series B proceeds partly to "expanding partnerships and integrations" (Crunchbase News (https://news.crunchbase.com/transportation/logistics-software-startup-seriesb-alvys/)); maintains 100+ connectors in-house | L68: 7 | M68: 3 | N68: Co-founder | O68: Series B proceeds partly go to 'expanding partnerships and integrations' - scale past 100 connectors without scaling integrations headcount. | P68: Your Series B coverage says part of the raise goes to 'expanding partnerships and integrations' - we help TMS teams scale past their first 100 connectors without scaling the integrations headcount. | Q68: Mature integrations; scale-the-tail pitch | R68: Nick Darman (Founder & CEO); Leo Gorodinski (⚠️ Former Co-Founder & CTO (Oct 2020–Feb 2026; now Founder at Cohesive Systems)) | S68: =COUNTIF(Contacts!$A:$A,A68) -> 2
A69: Cargado | B69: cargado.com | C69: USA | D69: US vertical | F69: Logistics - cross-border | G69: Invite-only load board for US–Mexico freight | H69: Series A $12M, Apr 2025 (Built In Chicago (https://www.builtinchicago.org/articles/cargado-raises-12m-series-a-20250408)) | J69: "Integrated marketplace" positioning; brokers/carriers run own TMSs → connector roadmap implied (blog (https://cargado.com/blog/cargado-raises-12m-to-build-integrated-cross-border-freight-marketplace/)); no public integrations directory | L69: 7 | M69: 3 | N69: Co-founder | O69: You are building the 'integrated' cross-border marketplace - embedded TMS and customs-broker connectors are the productized version of that promise. | P69: You're building the 'integrated' cross-border marketplace - embedded TMS and customs-broker connectors for your 200+ customers are exactly what ByteChef productizes for logistics platforms. | Q69: Inferred pain; very young company | R69: Matt Silver (Co-Founder & CEO); Rylan Hawkins (Co-Founder & CTO) | S69: =COUNTIF(Contacts!$A:$A,A69) -> 2
A70: Otto | B70: otto.vet | C70: USA | D70: US vertical | F70: Health - veterinary | G70: Client engagement + payments for vet clinics (ex-TeleVet) | H70: Series B $43M, Aug 2023 (Business Wire (https://www.businesswire.com/news/home/20230831425472/en/TeleVet-Announces-$43-Million-Series-B-on-the-Heels-of-Record-Growth-Rebrands-as-Otto)) | J70: Competes on PIMS integration breadth - each a hand-built sync (VetSoftwareHub (https://www.vetsoftwarehub.com/product/otto)) | L70: 7 | M70: 3 | N70: Co-founder | O70: Extend your PIMS coverage lead to every long-tail PIMS without hand-building each sync. | P70: Otto leads the category on PIMS coverage - Cornerstone, AVImark, ezyVet and the rest - and ByteChef would let you extend that lead to every long-tail PIMS without hand-building each sync. | Q70: May exceed 200 employees - verify | R70: Zeynep Young (CEO) | S70: =COUNTIF(Contacts!$A:$A,A70) -> 1
A71: Rose Rocket | B71: roserocket.com | C71: Canada | D71: US vertical | F71: Logistics - TMS | G71: Network-centric TMS for trucking/3PLs | H71: Series B $38M ($69M total), Jun 2023 (Business Wire (https://www.businesswire.com/news/home/20230620643042/en/Rose-Rocket-Raises-$38M-USD-Series-B-to-Scale-its-Network-Centric-TMS-Solutions-while-Expanding-into-the-Enterprise)) | J71: Platform Partner Program asks third parties to build against its SDK - demand exceeds in-house capacity (integration-partners (https://www.roserocket.com/integration-partners)) | L71: 7 | M71: 3 | N71: Co-founder | O71: Your Platform Partner Program asks partners to build against your SDK - flip the model and own the long-tail integrations in-product. | P71: Your Platform Partner Program asks partners to build against your SDK - ByteChef flips that model so your own team ships and owns the long-tail integrations customers ask for, white-labeled inside Rose Rocket. | Q71: Mature partner program; scale-the-tail pitch | R71: Alexander Luksidadi (Founder & CTO) | S71: =COUNTIF(Contacts!$A:$A,A71) -> 1
A72: Documenso | B72: documenso.com | C72: Germany/USA | D72: Dev tools | F72: E-signature | G72: Open-source e-signature (DocuSign alt) | H72: Pre-seed ~$1.5–2.2M OSS Capital (Product Hunt (https://www.producthunt.com/products/documenso)) | I72: ~10 | J72: n8n integration in public backlog (backlog #7 (https://github.com/documenso/backlog/issues/7)) | K72: 1/1/2/1/1 | L72: 6 | M72: 3 | N72: Ivica | O72: The n8n integration is queued in your public backlog behind core signing work - Zapier-class connectivity without touching your roadmap. | P72: Your public backlog has the n8n integration queued behind core signing work - as a fellow open-source company, ByteChef could be the embedded integration layer that ships Zapier-class connectivity for Documenso without touching your roadmap. | Q72: May be under 10 people; incorporation ambiguous | R72: Timur Ercan (Co-Founder & CEO) | S72: =COUNTIF(Contacts!$A:$A,A72) -> 1
A73: Pylon | B73: usepylon.com | C73: USA | D73: Dev tools | F73: Customer support | G73: B2B-native support (Slack/Teams-first) | H73: Series B $31M Aug 2025 (blog (https://www.usepylon.com/blog/announcing-our-31m-series-b)) | I73: unknown; hiring 23 roles | J73: Integration-heavy category + hiring surge; no direct pain artifact found | K73: 2/1/1/2/0 | L73: 6 | M73: 3 | N73: Ivica | O73: Every deal hinges on another Slack-Teams-Salesforce-Jira permutation - before the post-Series-B hiring wave goes to connector maintenance. | P73: Every Pylon deal seems to hinge on another Slack-Teams-Salesforce-Jira permutation - before your post-Series B hiring wave goes to connector maintenance, worth seeing how an embedded open-source iPaaS handles that long tail. | Q73: No direct pain artifact found - verify first | R73: Marty Kausas (Co-Founder & CEO); Advith Chelikani (Co-Founder) | S73: =COUNTIF(Contacts!$A:$A,A73) -> 2
A74: Zenskar | B74: zenskar.com | C74: USA | D74: HR/fin-ops | F74: Billing / rev-rec | G74: AI-native billing and revenue automation for B2B | H74: Series A $15M, Apr 2026 (BusinessWire (https://www.businesswire.com/news/home/20260416872552/en/Zenskar-Raises-$15-Million-Series-A-to-Expand-Agentic-Capabilities-for-B2B-Revenue-Automation)) | I74: unknown (Series A scale) | J74: Weakest signal: markets "200+ integrations" with two-way sync - maintaining that at Series A headcount is itself the cost problem; no public complaints found (comparison (https://www.zenskar.com/comparison/zonebilling-vs-ordway), G2 (https://www.g2.com/products/zenskar/reviews)) | L74: 6 | M74: 3 | N74: Ivica | O74: Promising 200+ two-way integrations on a Series A team is a permanent maintenance tax - worth comparing notes on running that catalog embedded. | P74: Promising 200+ two-way integrations with a Series A-sized team means a permanent maintenance tax - worth comparing notes on running that catalog on an embedded open-source integration platform instead. | Q74: Weakest evidence in segment | R74: Apurv Bansal (Co-Founder & CEO); Saurabh Agrawal (Co-Founder & CTO/CFO) | S74: =COUNTIF(Contacts!$A:$A,A74) -> 2
A75: SPRY | B75: sprypt.com | C75: USA | D75: US vertical | F75: Health - outpatient rehab | G75: EMR + RCM for PT/OT/speech clinics | H75: Series B, $25M total (Tracxn (https://tracxn.com/d/companies/spry/__pLjNtk5sG3VphYUFibwdCbJtfwj5SjzDjmUWwYDN5og)) | J75: Inferred only: enterprise upmarket motion implies EHR/clearinghouse integration asks (enterprise EMR post (https://www.sprypt.com/blog/enterprise-emr-physical-therapy)) | L75: 6 | M75: 3 | N75: Co-founder | O75: Enterprise rehab deals bring EHR and clearinghouse integration asks - say yes without pulling engineers off the core EMR. | P75: As SPRY pushes into enterprise rehab groups, every deal brings an EHR and clearinghouse integration ask - ByteChef lets you say yes without pulling engineers off the core EMR. | Q75: Weakest evidence in segment; 236 employees | R75: Brijraj Bhuptani (Co-Founder & CEO) | S75: =COUNTIF(Contacts!$A:$A,A75) -> 1
A76: Rentlio | B76: rentl.io | C76: Croatia | D76: Croatia | E76: Vertical SaaS | F76: Hospitality (PMS / channel manager) | G76: Cloud PMS, channel manager and booking engine for SE-European hotels and apartments | H76: Infinum Ventures partnership 2022 (about (https://rentl.io/en/about-us)); HAMAG-BICRO loan 2020; no VC round found | I76: 23–39 (ZoomInfo (https://www.zoominfo.com/c/rentlio/429753095)); IT team about 10 | J76: Fiskalizacija 2.0 e-invoicing supports only one intermediary, moj-eRačun (help (https://help.rentl.io/en/articles/10515786-moj-e-racun)); unlisted integrations go to an integrations@ inbox (integrations (https://rentl.io/en/integrations)); reviews want better accounting info (HTR (https://hoteltechreport.com/operations/property-management-systems/rentlio)), seen only as a search summary | K76: 2/2/3/2/1 | L76: 10 | M76: 1 | N76: Co-founder | O76: Your eRačun flow runs through moj-eRačun alone and anything else goes to an integrations@ inbox. We'd let Rentlio ship white-label connectors to every intermediary, accounting tool and lock vendor your hoteliers ask for, without your dev team building each one. | P76: Your eRačun flow runs through moj-eRačun alone and anything else goes to an integrations@ inbox. We'd let Rentlio ship white-label connectors to every intermediary, accounting tool and lock vendor your hoteliers ask for, without your dev team building each one. | Q76: Review-site complaint from a search summary | R76: Ivan Padavić (CTO and co-founder); Marko Mišulić (CEO and co-founder) | S76: =COUNTIF(Contacts!$A:$A,A76) -> 2
A77: Lemax | B77: lemax.net | C77: Croatia | D77: Croatia | E77: Vertical SaaS | F77: Travel (tour-operator / DMC software) | G77: Cloud reservation and back-office system for multi-day tour operators and DMCs | H77: Private, unfunded (Tracxn (https://tracxn.com/d/companies/lemax/__Q6tQlVe_fCoy8EP_fZiqhCR86GDhobOolu2URzlahmA)) | I77: "Team of 70+" (careers (https://lemax.net/careers-and-jobs/)) | J77: Ready-made accounting connectors only for QuickBooks and Oracle ERP; everyone else told to "use our Accounting API" (finance page (https://lemax.net/finances-and-accounting/)); hiring implementation consultants | K77: 2/2/2/2/1 | L77: 9 | M77: 1 | N77: Co-founder | O77: Lemax ships QuickBooks and Oracle, and every other tour operator gets an API and a to-do list. An embedded integration layer would let you offer native Xero, DATEV, Pantheon and eRačun connectors under the Lemax brand. | P77: Lemax ships QuickBooks and Oracle, and every other tour operator gets an API and a to-do list. An embedded integration layer would let you offer native Xero, DATEV, Pantheon and eRačun connectors under the Lemax brand. | Q77: Verify CTO is still in role | R77: Marko Elezović (CTO / Head of Engineering (may have moved on)); Mate Kostovski (CEO) | S77: =COUNTIF(Contacts!$A:$A,A77) -> 2
A78: AGRIVI | B78: agrivi.com | C78: Croatia | D78: Croatia | E78: Vertical SaaS | F78: Agritech (farm management) | G78: Farm management and agri-food data platform for growers, food companies and co-ops | H78: Series A €4M (SCV, EIF, HBOR) (Tech.eu (https://tech.eu/2020/11/17/agtech-agrivi-funding-farm-management-software)); about $7.3M total (Tracxn (https://tracxn.com/d/companies/agrivi/__BJv6Gfe3_socGZLvcMNV__bJDSRupJiXPgTFhYkJFEI)) | I78: about 40 (Craft (https://craft.co/agrivi)) | J78: Has an "Integration Partner" tier to deliver ERP, CRM, BI, IoT and custom integrations per customer (partner program (https://www.agrivi.com/partner-program/)), so enterprise integrations are bespoke; also has a business API for SAP and MS Dynamics | K78: 2/2/2/2/1 | L78: 9 | M78: 1 | N78: Co-founder | O78: Your partner program exists to hand-build ERP, CRM and BI integrations for each enterprise customer. We'd turn those one-off projects into a white-label connector catalogue inside AGRIVI. | P78: Your partner program exists to hand-build ERP, CRM and BI integrations for each enterprise customer. We'd turn those one-off projects into a white-label connector catalogue inside AGRIVI. | R78: Matija Žulj (Founder and CEO) | S78: =COUNTIF(Contacts!$A:$A,A78) -> 1
A79: Nokumo | B79: nokumo.net | C79: Croatia | D79: Croatia | E79: Vertical SaaS | F79: Hospitality (PMS) | G79: Hotel and vacation-rental PMS with fiscal compliance for HR, SI, DE, AT, IT and CH | H79: Bootstrapped; founding capital from SmartIT and Infranet (incorporation (https://www.nokumo.net/en/incorporation-information)) | I79: about 9 named (about (https://www.nokumo.net/about-us)); ZoomInfo conflicts (1–10 vs 50–100) | J79: Three accounting/ERP connectors, with Pantheon and two POS (Elektronček, Mikrogram) "coming soon"; ViDA on the roadmap; six fiscal regimes (integrations (https://www.nokumo.net/integrations)); its own positioning is against "EUR 5,000 for a fiscal integration" | K79: 2/1/3/2/1 | L79: 9 | M79: 1 | N79: Co-founder | O79: Pantheon and two POS connectors are still 'coming soon' while you expand across six fiscal jurisdictions. We'd let a small team ship white-label accounting and POS connectors without each one taking a sprint. | P79: Pantheon and two POS connectors are still 'coming soon' while you expand across six fiscal jurisdictions. We'd let a small team ship white-label accounting and POS connectors without each one taking a sprint. | Q79: Headcount and founding year conflict | R79: Marko Brković (CTO); Nikola Crnković (CPO / CRO) | S79: =COUNTIF(Contacts!$A:$A,A79) -> 2
A80: Mireo | B80: mireo.com | C80: Croatia | D80: Croatia | E80: Vertical SaaS | F80: Logistics (fleet telematics) | G80: GPS navigation SDKs and Mireo Fleet vehicle-tracking SaaS | H80: Private, no VC (Wikipedia (https://en.wikipedia.org/wiki/Mireo)) | I80: about 61 (ZoomInfo (https://www.zoominfo.com/c/mireo/425122535)), from a search summary | J80: ERP integration is DIY: customers request an API key and docs; fuel cards and tachograph are the only packaged integrations (Mireo Fleet (https://www.mireo.com/mireofleet)) | K80: 2/2/2/2/1 | L80: 9 | M80: 1 | N80: Co-founder | O80: Today a Mireo Fleet customer who wants trip and fuel data in their ERP gets an API key and docs. Embedded, pre-built ERP, accounting and payroll connectors would remove that step. | P80: Today a Mireo Fleet customer who wants trip and fuel data in their ERP gets an API key and docs. Embedded, pre-built ERP, accounting and payroll connectors would remove that step. | R80: Ivica Siladić (CTO and co-founder) | S80: =COUNTIF(Contacts!$A:$A,A80) -> 1
A81: DotYourSpot | B81: dotyourspot.com | C81: Croatia | D81: Croatia | E81: Vertical SaaS | F81: Hospitality (restaurant tech) | G81: Restaurant, bar and hotel operations suite: menus, reservations, POS, reviews; 1,500+ venues | H81: Bootstrapped (Latka (https://getlatka.com/companies/dotyourspot.com)) | I81: 17–20 (Latka (https://getlatka.com/companies/dotyourspot.com)) | J81: 8 integrations, 2 of them its own products; only 2 cash registers (Remaris, Avail.IT), each shipped as its own page (integrations (https://www.dotyourspot.com/en/integrations)) | K81: 2/2/2/2/1 | L81: 9 | M81: 1 | N81: Co-founder | O81: With 1,500+ venues and two cash-register integrations, every venue on a different fiscal POS is a sales blocker. We'd let DotYourSpot ship the rest of the Croatian POS market as native connectors. | P81: With 1,500+ venues and two cash-register integrations, every venue on a different fiscal POS is a sales blocker. We'd let DotYourSpot ship the rest of the Croatian POS market as native connectors. | R81: Karlo Đuderija (CTO and co-founder); Zlatko Kovačić (CEO and founder) | S81: =COUNTIF(Contacts!$A:$A,A81) -> 2
A82: MMK Systems (Booking Manager) | B82: booking-manager.com | C82: Croatia | D82: Croatia | E82: Vertical SaaS | F82: Travel (yacht charter) | G82: Charter booking and back office: 1,300+ fleet operators, 5,000+ agents | H82: No funding found; founder-led (our story (https://www.mmksystems.com/en/our-story.html)) | I82: about 32 (CB Insights (https://www.cbinsights.com/company/mmk-booking-manager)) | J82: Indirect: REST API for agencies (API (http://balancer1.mmksystems.com/en/products/rest-api.html)); agencies hire third parties to build on it (Goigo (https://www.goigo.agency/en/web-applications/laravel-cms-system-for-charter-agencies-nausys-booking-manager-mmk)); fiscalization support page 403 | K82: 2/2/1/2/1 | L82: 8 | M82: 2 | N82: Co-founder | O82: Croatian charter fleets now exchange eRačuns, and your agencies pay outside developers to connect to Booking Manager. Embedded white-label connectors would let MMK own both sides. | P82: Croatian charter fleets now exchange eRačuns, and your agencies pay outside developers to connect to Booking Manager. Embedded white-label connectors would let MMK own both sides. | Q82: Pain evidence indirect | R82: Marko Gnjidić (Founder and CEO) | S82: =COUNTIF(Contacts!$A:$A,A82) -> 1
A83: NauSYS (Stratus IT) | B83: nausys.com | C83: Croatia | D83: Croatia | E83: Vertical SaaS | F83: Travel (yacht-charter distribution) | G83: Real-time charter booking network: about 900 fleets ↔ 5,000 agencies | H83: Private (Crunchbase (https://www.crunchbase.com/organization/nausys)) | I83: 11–50 (CB Insights (https://www.cbinsights.com/company/nausys)) | J83: Indirect: API or iFrame only; third parties build the apps and CMSs (iBS (https://www.ibs.gr/en/yachts-booking-application-connected-to-nausys/), Goigo (https://www.goigo.agency/en/blog/yacht-charter-api-solutions)) | K83: 2/2/1/2/1 | L83: 8 | M83: 2 | N83: Co-founder | O83: Fleets and agencies pay outside developers to connect NauSYS to their ERPs and websites. We'd let you offer those connections natively, under your brand. | P83: Fleets and agencies pay outside developers to connect NauSYS to their ERPs and websites. We'd let you offer those connections natively, under your brand. | Q83: Pain evidence indirect | R83: Goran Pavešić (CEO and co-founder); Luka Surija (CTO) | S83: =COUNTIF(Contacts!$A:$A,A83) -> 2
A84: Bitreport | B84: getbitreport.com | C84: Croatia | D84: Croatia | E84: Vertical SaaS | F84: Retail (chain-store ops) | G84: Task, audit and checklist platform for chains (Domino's, Levi's, Under Armour) | H84: €300k, Purple Ventures, Nov 2024 (Tech.eu (https://tech.eu/2024/11/19/croatian-saas-startup-bitreport-raises-eur300000-for-chain-store-management/)) | I84: unknown (small) | J84: Its own guide says it "does not replace your POS, inventory ledger, ERP" and tells buyers to confirm data exchange with those vendors (blog (https://getbitreport.com/blog/retail-store-management-software/)); no integrations listed | K84: 2/1/2/2/1 | L84: 8 | M84: 2 | N84: Co-founder | O84: Your own buying guide tells chains to sort out POS and ERP data exchange themselves. Embedded connectors would let Bitreport pull sales and staffing data into audits on day one. | P84: Your own buying guide tells chains to sort out POS and ERP data exchange themselves. Embedded connectors would let Bitreport pull sales and staffing data into audits on day one. | R84: Domagoj Rade (CTO and co-founder); Marko Čačić (CEO and co-founder) | S84: =COUNTIF(Contacts!$A:$A,A84) -> 2
A85: Ascalia | B85: ascalia.io | C85: UK | D85: Croatia | E85: Vertical SaaS | F85: Manufacturing (Industry 4.0 / MES) | G85: Edge-AI MES: traceability, predictive maintenance, quality | H85: Bootstrapped about $1.6M revenue (Latka (https://getlatka.com/companies/ascalia)) or about $1.05M raised from grants and Fil Rouge (PitchBook (https://pitchbook.com/profiles/company/442252-54)) | I85: 19–30 (EIT Hub (https://eitmanufacturinghub.hr/profil-kompanije-ascalia/)) | J85: ERP integration is a module built to each customer's needs (EIT Hub (https://eitmanufacturinghub.hr/profil-kompanije-ascalia/)) | K85: 2/2/2/1/0 | L85: 7 | M85: 3 | N85: Co-founder | O85: Each Ascalia factory roll-out includes a custom ERP integration. A white-label connector layer would make SAP, Pantheon and Business Central hookups configuration rather than project work. | P85: Each Ascalia factory roll-out includes a custom ERP integration. A white-label connector layer would make SAP, Pantheon and Business Central hookups configuration rather than project work. | Q85: Pain evidence from a search summary; UK HQ | S85: =COUNTIF(Contacts!$A:$A,A85) -> 0
A86: Productive | B86: productive.io | C86: Croatia | D86: Croatia | E86: Horizontal B2B, HR and fin-ops SaaS | F86: Agency PSA | G86: All-in-one agency management: sales, budgeting, resourcing, PM, billing | H86: Self-funded, profitable (about (https://productive.io/about-us/)); about $6.8M ARR (Latka (https://getlatka.com/companies/productive)) | I86: 100+ (LinkedIn (https://www.linkedin.com/company/productive-io)) | J86: About 27 hand-built connectors (8 accounting, 9+ HRIS), with Zapier for the long tail (integrations (https://productive.io/integrations/)); G2: "lack of integrations" (G2 (https://www.g2.com/products/productive/reviews?page=4)) | K86: 2/2/3/2/1 | L86: 10 | M86: 1 | N86: Ivica | O86: You've built Fortnox, Twinfield, Exact and nine HRIS connectors one by one and still send the rest to Zapier. ByteChef lets your agencies connect the next 50 accounting and HR tools natively, under the Productive brand. | P86: You've built Fortnox, Twinfield, Exact and nine HRIS connectors one by one and still send the rest to Zapier. ByteChef lets your agencies connect the next 50 accounting and HR tools natively, under the Productive brand. | R86: Tomislav Car (Founder and CEO); Ivan Lučin (VP Engineering) | S86: =COUNTIF(Contacts!$A:$A,A86) -> 2
A87: Farseer | B87: farseer.com | C87: Croatia | D87: Croatia | E87: Horizontal B2B, HR and fin-ops SaaS | F87: FP&A | G87: AI planning, forecasting and reporting on top of ERPs | H87: Series A $7.2M, AYMO Ventures (SeeNews (https://seenews.com/news/croatias-farseer-raises-7-2-mln-in-series-a-funding-1289803)) | I87: about 79–87 (Tracxn (https://tracxn.com/d/companies/farseer/__x0lLhMMLZoeUP0mFYa1er93Dhaiusvq0ljFsbpA69qg)) | J87: Pre-built SAP, Oracle, NetSuite, Workday and Salesforce connectors, plus a "custom connector framework" (integrations (https://www.farseer.com/platform/integrations/)); Series A money partly goes to implementation specialists (Netokracija (https://www.netokracija.com/farseer-investicija-serija-a-zaposljavanje-matija-nakic-241639)) | K87: 2/2/3/2/1 | L87: 10 | M87: 1 | N87: Ivica | O87: Your Series A is paying for implementation specialists to wire Farseer into each customer's ERP. An embeddable, open-source connector engine would turn that into self-serve setup as you push into the US. | P87: Your Series A is paying for implementation specialists to wire Farseer into each customer's ERP. An embeddable, open-source connector engine would turn that into self-serve setup as you push into the US. | R87: Luka Mijatović (Co-founder and CTO); Matija Nakić (Co-founder and CEO) | S87: =COUNTIF(Contacts!$A:$A,A87) -> 2
A88: TalentLyft | B88: talentlyft.com | C88: Croatia | D88: Croatia | E88: Horizontal B2B, HR and fin-ops SaaS | F88: HR tech (ATS) | G88: Recruitment marketing, ATS and talent CRM for SMBs | H88: Mostly bootstrapped; $300K seed in 2017 (Netokracija (https://www.netokracija.com/talentlyft-saas-bootstraped-161428)) | I88: 11–50 (StartupBlink (https://www.startupblink.com/top-startups/croatia/software-data)) | J88: About 9 third-party integrations, no Zapier (integrations (https://www.talentlyft.com/integrations), Software Advice (https://www.softwareadvice.com/hr/talentlyft-profile/)); customers reach it through Merge (Merge (https://www.merge.dev/integrations/talentlyft)) | K88: 2/2/2/2/1 | L88: 9 | M88: 1 | N88: Ivica | O88: Your customers already reach TalentLyft through Merge and Unified. Embedding the HRIS and payroll hand-offs in your own product keeps that relationship, and the margin, with you. | P88: Your customers already reach TalentLyft through Merge and Unified. Embedding the HRIS and payroll hand-offs in your own product keeps that relationship, and the margin, with you. | Q88: Verify CTO is still in role | R88: Nikola Biondić (Co-founder and CTO (headline now reads "Hidden Talent"; check)); Mario Buntić (Co-founder and CEO) | S88: =COUNTIF(Contacts!$A:$A,A88) -> 2
A89: Oradian | B89: oradian.com | C89: Croatia | D89: Croatia | E89: Horizontal B2B, HR and fin-ops SaaS | F89: Fintech infra (core banking) | G89: Cloud core banking (Instafin) for lenders and MFIs in emerging markets | H89: VC-backed (Fil Rouge, SBI and others); totals inconsistent (Tracxn (https://tracxn.com/d/companies/oradian/__Ho3hLUqK6LAslKsLh7pfq2NeIlpZJNTwHDmwS2fyC7Y)) | I89: 66–67 (Tracxn (https://tracxn.com/d/companies/oradian/__Ho3hLUqK6LAslKsLh7pfq2NeIlpZJNTwHDmwS2fyC7Y)) | J89: Builds custom connectors with each lender for KYC, payments, fraud and wallets (APIs & Integrations (https://oradian.com/apis-integrations)); hiring a CTO (job (https://app.screenloop.com/careers/oradian/job_posts/8265?tab=overview)) | K89: 2/2/3/1/1 | L89: 9 | M89: 1 | N89: Ivica | O89: You co-build a custom connector with each lender for KYC, payments and fraud. A white-label integration layer would let partners self-connect, and it would be a quick win for your incoming CTO. | P89: You co-build a custom connector with each lender for KYC, payments and fraud. A white-label integration layer would let partners self-connect, and it would be a quick win for your incoming CTO. | R89: Rikard Pavelić (CTO (a CTO search is open)); Antonio Separović (CEO and co-founder) | S89: =COUNTIF(Contacts!$A:$A,A89) -> 2
A90: OptimoRoute | B90: optimoroute.com | C90: US (Palo Alto) | D90: Croatia | E90: Horizontal B2B, HR and fin-ops SaaS | F90: Route and field scheduling | G90: Route optimization and scheduling for delivery and field-service teams | H90: Series A $6.5M (Latka (https://getlatka.com/companies/optimoroute)) | I90: about 59 (Tracxn (https://tracxn.com/d/companies/optimoroute/__Ke8oEXQvD2AzJQD6E8B59E6OKx9ZPVJBklTBz9fZwX0)) | J90: Customers build their own SAP, Dynamics, NetSuite and Shopify feeds via the Web Service API, supported by an implementation-engineering team (API page (https://optimoroute.com/web-service-api/)); /integrations 404 | K90: 2/2/3/1/0 | L90: 8 | M90: 2 | N90: Ivica | O90: Your implementation engineers walk every customer through building their own SAP or NetSuite feed. Pre-built, white-label order and ERP connectors would remove that step from onboarding. | P90: Your implementation engineers walk every customer through building their own SAP or NetSuite feed. Pre-built, white-label order and ERP connectors would remove that step from onboarding. | Q90: US HQ; /integrations page 404 | R90: Frane Šarić (Co-founder and CTO); Goran Kukolj (Co-founder) | S90: =COUNTIF(Contacts!$A:$A,A90) -> 2
A91: Hypefy | B91: hypefy.ai | C91: Croatia | D91: Croatia | E91: Horizontal B2B, HR and fin-ops SaaS | F91: Martech (influencer) | G91: AI influencer marketing: discovery, campaigns, payments, reporting | H91: Series A $7.2M, AYMO, 2026 (FinSMEs (https://www.finsmes.com/2026/07/hypefy-ai-raises-7-2m-in-series-a-funding.html)) | I91: 49, growing to about 100 (Tracxn (https://tracxn.com/d/companies/hypefy/__NsEzjMCfMYWwtvR708uI5R2aKIipUlXuPpmICKg_pUQ)) | J91: Indirect: native integrations limited to Instagram and TikTok (Capterra (https://www.capterra.com/p/10027168/Hypefy/)) while it sells to D2C brands on Shopify and CRM stacks | K91: 2/2/1/2/1 | L91: 8 | M91: 2 | N91: Ivica | O91: You sell ROI to D2C brands but connect only to Instagram and TikTok. Embedded Shopify, CRM and attribution connectors would let you prove revenue per creator before the US push. | P91: You sell ROI to D2C brands but connect only to Instagram and TikTok. Embedded Shopify, CRM and attribution connectors would let you prove revenue per creator before the US push. | Q91: Pain evidence indirect | R91: Stjepan Zelić (Co-founder and CEO); Filip Špiranec / Davor Šibenik (CTO (sources disagree on which)) | S91: =COUNTIF(Contacts!$A:$A,A91) -> 2
A92: Determ | B92: determ.com | C92: Croatia | D92: Croatia | E92: Horizontal B2B, HR and fin-ops SaaS | F92: Martech (media monitoring) | G92: Media monitoring, social listening and data API (formerly Mediatoolkit) | H92: Unknown; Bornfight an investor (CB Insights (https://www.cbinsights.com/company/mediatoolkit)) | I92: 11–50 (Crunchbase (https://www.crunchbase.com/organization/mediatoolkit)) | J92: Integrations are Slack, Zapier, API and webhooks only (EuropeanStack (https://europeanstack.com/software/determ)) | K92: 1/2/2/2/1 | L92: 8 | M92: 2 | N92: Ivica | O92: Determ alerts go to Slack and Zapier today. Embedded HubSpot, Salesforce and Zendesk connectors would turn a mention into a lead or a ticket inside your product. | P92: Determ alerts go to Slack and Zapier today. Embedded HubSpot, Salesforce and Zendesk connectors would turn a mention into a lead or a ticket inside your product. | R92: Tomislav Grubišić (Co-founder and CEO) | S92: =COUNTIF(Contacts!$A:$A,A92) -> 1
A93: Treblle | B93: treblle.com | C93: Croatia | D93: Croatia | E93: Horizontal B2B, HR and fin-ops SaaS | F93: Dev tools (API observability) | G93: API monitoring, analytics, security and docs | H93: $8.4M total incl. $7M from Nauta (Techloy (https://www.techloy.com/croatian-treblle-raises-7-million/)) | I93: 22+ (about (https://treblle.com/about-us)) | J93: API-gateway connectors shipped one at a time: AWS, Azure APIM, Kong, MuleSoft, WSO2, Traefik, Apigee (docs (https://docs.treblle.com/integrate-treblle/api-gateways/kong)); no evidence of alerting or ITSM connectors | K93: 2/2/1/1/1 | L93: 7 | M93: 3 | N93: Ivica | O93: You've built gateway plugins one by one. An embedded connector layer could carry Treblle's API insights into Jira, ServiceNow and PagerDuty without a new team for each target. | P93: You've built gateway plugins one by one. An embedded connector layer could carry Treblle's API insights into Jira, ServiceNow and PagerDuty without a new team for each target. | Q93: Pain evidence partial | R93: Vedran Cindrić (Founder and CEO) | S93: =COUNTIF(Contacts!$A:$A,A93) -> 1
A94: Legit (Data Privacy Manager) | B94: legit.eu | C94: Croatia | D94: Croatia | E94: Horizontal B2B, HR and fin-ops SaaS | F94: Privacy / compliance | G94: Privacy automation: ROPA, data discovery, DSARs, removal orchestration | H94: €650K, Vesna Deeptech (Legit (https://legit.eu/news/legit-secures-investment-from-vesna-deeptech-vc-fund-to-accelerate-growth-of-data-privacy-manager-solution/)) | I94: unknown; 200+ customers | J94: Indirect: sells "Data Removal Orchestration" across customer systems but publishes no named connectors (DPM (https://legit.eu/news/data-privacy-manager/)) | K94: 2/1/2/1/1 | L94: 7 | M94: 3 | N94: Ivica | O94: Removal orchestration is only as good as the systems it reaches. Open-source, embeddable connectors to CRMs, HRIS and SaaS would let DPM fulfil DSARs end to end. | P94: Removal orchestration is only as good as the systems it reaches. Open-source, embeddable connectors to CRMs, HRIS and SaaS would let DPM fulfil DSARs end to end. | Q94: Pain evidence indirect | R94: Marijan Bračić (Board president (strategy, R&D, product)) | S94: =COUNTIF(Contacts!$A:$A,A94) -> 1
A95: Tomsoft (Luceed ERP) | B95: tomsoft.hr | C95: Croatia | D95: Croatia | E95: Fiskalizacija 2.0: e-invoicing and SMB ERP | F95: SMB / mid-market ERP | G95: Modular Luceed ERP (24 modules) with a REST API, for retailers, distributors, hospitality | H95: Bootstrapped since 1994 (Fina (https://infobiz.fina.hr/tvrtka/tomsoft-d-o-o/OIB-28658131868)) | I95: 32; €2.56M revenue 2025 (Fina (https://infobiz.fina.hr/tvrtka/tomsoft-d-o-o/OIB-28658131868)) | J95: Own docs: "almost 30 different intermediaries" exist, Luceed supports 2 (Omnizon, mer) and dropped HT EDI (docs (https://docs.tomsoft.hr/fiskalizacija-2-0/tomsoft-rjesenje-za-fiskalizaciju-2)); webshop links (Magento, Shopify) built per client by agencies (Inchoo (https://inchoo.hr/luceed-magento-integracija/)); hiring a REST-API developer (careers (https://www.tomsoft.hr/en/careers/)) | K95: 2/2/3/2/1 | L95: 10 | M95: 1 | N95: Ivica | O95: Your Fiskalizacija docs say there are almost 30 intermediaries and Luceed supports two. What if Luceed could offer every intermediary, plus Shopify and Magento, as native white-label connectors? | P95: Your Fiskalizacija docs say there are almost 30 intermediaries and Luceed supports two. What if Luceed could offer every intermediary, plus Shopify and Magento, as native white-label connectors? | R95: Tomislav Ivančević (Founder and director) | S95: =COUNTIF(Contacts!$A:$A,A95) -> 1
A96: Micronic (KISERP / KIS4WIN) | B96: micronic.hr | C96: Croatia | D96: Croatia | E96: Fiskalizacija 2.0: e-invoicing and SMB ERP | F96: Accounting / ERP | G96: Bookkeeping and ERP suite for accounting firms and manufacturers | H96: Private, 7 owners (Fina (https://infobiz.fina.hr/tvrtka/micronic-d-o-o/OIB-89489773101)) | I96: 15; about €1.0M revenue (Fina (https://infobiz.fina.hr/tvrtka/micronic-d-o-o/OIB-89489773101)) | J96: Built and announced 6 intermediary integrations one at a time: mStart, Super eRačun, ePoslovanje, monoform, ePošta, Moj eRačun (integrations (https://www.micronic.hr/oznake/integracija/)) | K96: 2/2/3/1/1 | L96: 9 | M96: 1 | N96: Ivica | O96: You've shipped six intermediary integrations for KISERP, each one its own project. An embedded integration layer could let you add the next 28 intermediaries, and your clients' webshops, as configuration instead of code. | P96: You've shipped six intermediary integrations for KISERP, each one its own project. An embedded integration layer could let you add the next 28 intermediaries, and your clients' webshops, as configuration instead of code. | R96: Igor Janjić (Management board member) | S96: =COUNTIF(Contacts!$A:$A,A96) -> 1
A97: E-RAČUNI | B97: e-racuni.com/hrracuni | C97: Slovenia (Maribor) | D97: Croatia | E97: Fiskalizacija 2.0: e-invoicing and SMB ERP | F97: Cloud invoicing / ERP and intermediary | G97: Cloud business software that is also a certified Croatian intermediary; about 10,000 Croatian companies | H97: Private, founder-owned (ebonitete (https://www.ebonitete.si/e-racuni-doo/)) | I97: about 10 at the SI parent; HR entity €1.26M revenue (Fina (https://infobiz.fina.hr/tvrtka/x/OIB-86196084068)) | J97: 8 webshop connectors listed one by one: Magento, WooCommerce, PrestaShop, Wix, Stripe, Squarespace, OpenCart, Shopify (e-racuni.hr (https://e-racuni.com/hrracuni/)) | K97: 2/1/3/2/1 | L97: 9 | M97: 1 | N97: Ivica | O97: You maintain eight webshop connectors by hand for about 10,000 Croatian customers. An embedded white-label integration engine could add the next 50 (ERPs, banks, marketplaces) without growing the team. | P97: You maintain eight webshop connectors by hand for about 10,000 Croatian customers. An embedded white-label integration engine could add the next 50 (ERPs, banks, marketplaces) without growing the team. | Q97: Slovenian HQ; confirm Croatian decision-maker | R97: David Gorišek (Founder and director) | S97: =COUNTIF(Contacts!$A:$A,A97) -> 1
A98: ViziBit (Vizibit eRačun) | B98: vizibit.hr/eracuni | C98: Croatia | D98: Croatia | E98: Fiskalizacija 2.0: e-invoicing and SMB ERP | F98: Intermediary, DMS and e-signature | G98: Paperless-office platform turned intermediary, aimed at accounting firms | H98: Private, founder-led (Fina (https://infobiz.fina.hr/tvrtka/x/OIB-65845322221)) | I98: 13; €1.65M revenue (Fina (https://infobiz.fina.hr/tvrtka/x/OIB-65845322221)) | J98: "API access for external integrations" marked COMING SOON; XLSX/XML import/export today (vizibit.hr (https://vizibit.hr/eracuni/)); dedicated "ERP integration" page for software vendors (page (https://vizibit.hr/eracuni/razvojne-tvrtke/)) | K98: 2/2/2/2/1 | L98: 9 | M98: 1 | N98: Ivica | O98: Your eRačun API is still 'coming soon' and customers import XLSX/XML today. We could give Vizibit ready-made, white-label connectors into the ERPs your accounting-firm customers already run. | P98: Your eRačun API is still 'coming soon' and customers import XLSX/XML today. We could give Vizibit ready-made, white-label connectors into the ERPs your accounting-firm customers already run. | R98: Robert Vurušić (Founder and CEO) | S98: =COUNTIF(Contacts!$A:$A,A98) -> 1
A99: RIS (Faros ERP, Ensolva) | B99: ris.hr | C99: Croatia | D99: Croatia | E99: Fiskalizacija 2.0: e-invoicing and SMB ERP | F99: SaaS ERP and procurement / AP | G99: Faros, one of the first Croatian SaaS ERPs, plus Ensolva procurement with central e-invoice intake | H99: Private, founder-owned (Fina (https://infobiz.fina.hr/tvrtka/ris-d-o-o/OIB-77917801452)) | I99: 50; €3.27M revenue (Fina (https://infobiz.fina.hr/tvrtka/ris-d-o-o/OIB-77917801452)) | J99: Faros has to generate e-invoice XML and integrate with intermediaries; Ensolva does "centralized eInvoice receipt" (RIS F2.0 (https://ris.hr/fiskalizacija-2-0-nova-era-digitalnog-poslovanja/)) | K99: 2/2/1/2/1 | L99: 8 | M99: 2 | N99: Ivica | O99: Ensolva pulls in supplier eInvoices from every intermediary and Faros pushes them out. An embedded integration layer could connect both to any intermediary or customer ERP without a new project each time. | P99: Ensolva pulls in supplier eInvoices from every intermediary and Faros pushes them out. An embedded integration layer could connect both to any intermediary or customer ERP without a new project each time. | Q99: Pain evidence indirect | R99: Mile Pavlić (Founder and CEO) | S99: =COUNTIF(Contacts!$A:$A,A99) -> 1
A100: Pupilla (Synesis) | B100: pupilla.hr | C100: Croatia | D100: Croatia | E100: Fiskalizacija 2.0: e-invoicing and SMB ERP | F100: Accounting / ERP | G100: Long-running small-business accounting program | H100: Private, sole founder (Fina (https://infobiz.fina.hr/tvrtka/pupilla-d-o-o/OIB-00343110335)) | I100: 9; €2.91M revenue (Fina (https://infobiz.fina.hr/tvrtka/pupilla-d-o-o/OIB-00343110335)) | J100: Built 5 separate e-invoice channels: mojeRačun, FINA B2G, FINA B2B, ePoslovanje, Redok (Synesis eRačun (https://www.pupilla.hr/synesis/efaktura/)) | K100: 2/1/3/1/1 | L100: 8 | M100: 2 | N100: Ivica | O100: Synesis already maintains five eInvoice channel integrations. We could turn that into a white-label connector catalogue covering every intermediary, so each new one is configuration, not a release. | P100: Synesis already maintains five eInvoice channel integrations. We could turn that into a white-label connector catalogue covering every intermediary, so each new one is configuration, not a release. | Q100: 9 employees | R100: Krunoslav Lisac (Founder and director) | S100: =COUNTIF(Contacts!$A:$A,A100) -> 1
...

Sheet Contacts
A1: company | B1: name | C1: role | D1: title_check | E1: linkedin | F1: confidence | G1: followed_on_linkedin | H1: note_draft | I1: status | J1: notes
A2: Plancraft | B2: Julian Wiedenhaus | C2: CEO & Co-founder | E2: https://www.linkedin.com/in/julianwiedenhaus/ | G2: Y | H2: Hi Julian - noticed Plancraft's DATEV workflow still leans on CSV export/import while you scale across 11 countries. We help construction-tech platforms ship real two-way accounting & supplier APIs fast. Worth a quick chat?
A3: Atlar | B3: Johannes Elgh | C3: CTO & Co-founder | E3: https://www.linkedin.com/in/jelgh/ | G3: Y | H3: Hi Johannes - saw Atlar is staffing a 9-engineer Connectivity team for bank/ERP integrations. Worth comparing notes on what an embedded open-source integration layer could take off that roadmap?
A4: Hyperline | B4: Clément Garbay | C4: Co-founder & CTO | E4: https://www.linkedin.com/in/clementgarbay/ | G4: Y | H4: Hi Clément - your changelog shows accounting connectors shipping one at a time (Zoho Books, then NetSuite/Rillet). We help teams like Hyperline ship ten a quarter without burning core eng. Open to a quick chat?
A5: Payslip | B5: Fidelma McGuirk | C5: Founder & CEO | E5: https://www.linkedin.com/in/fidelmamcguirk/ | G5: Y | H5: Hi Fidelma - noticed Payslip's team hand-builds every HCM-to-payroll connector (Workday PECI, SuccessFactors). We turn that workload into configuration on an embedded platform. Worth a quick chat?
A6: Sequence | B6: Riya Grover | C6: Co-founder & CEO | E6: https://www.linkedin.com/in/riya-grover-a22a4822/ | G6: Y | H6: Hi Riya - Sequence's docs route NetSuite customers to CSV exports and "talk to our team." We help billing platforms make NetSuite (and the next ten ERPs) native. Worth a quick chat?
A7: Zelt | B7: Chris Priebe | C7: Co-founder & CEO | E7: https://www.linkedin.com/in/chrisagain/ | G7: Y | H7: Hi Chris - reviews of Zelt flag the missing integration ecosystem and public API. An embedded iPaaS gives you both, plus fixes for things like the Nest pension sync. Worth a quick chat?
A8: Coperniq | B8: Abdullah Al-Zandani | C8: CEO | E8: https://www.linkedin.com/in/azandani/ | G8: Y | H8: Hi Abdullah - Coperniq's support docs list ~8 native integrations, with the rest routed through Zapier. We help teams ship that long tail natively and white-labeled. Worth a quick chat?
A9: Latchel | B9: Ethan Lieber | C9: CEO & Co-founder | E9: https://www.linkedin.com/in/ethanlieber/ | G9: Y | H9: Hi Ethan - congrats on the Series A. Saw the funds are earmarked to deepen third-party property management integrations - we help compress that roadmap from quarters to weeks. Worth a quick chat?
A10: Lawmatics | B10: Matt Spiegel | C10: Founder & CEO | E10: https://www.linkedin.com/in/mattspiegelesq/ | G10: Y | H10: Hi Matt - G2 reviewers praise Lawmatics' automation but repeatedly flag integrations as a weak spot. We help close that gap without staffing a connector team. Worth a quick chat?
A11: Checkly | B11: Hannes Lenke | C11: CEO | E11: https://www.linkedin.com/in/hanneslenke/ | G11: Y | H11: Hi Hannes - Checkly's alert-channel list is a fraction of Datadog's, and the community has filed integration requests for years. We help you match that catalog breadth at startup cost. Worth a quick chat?
A12: Infisical | B12: Maidul Islam | C12: Co-founder | E12: https://www.linkedin.com/in/maidul98/ | G12: Y | H12: Hi Maidul - secret-sync bugs like the GitLab masked-sync failure have sat open since 2024 across Infisical's hand-built connectors. We maintain 190+ so yours don't rot. Worth a quick chat?
A13: Plane | B13: Vamsi Kurama | C13: CEO & Co-founder | E13: https://www.linkedin.com/in/vamsi-kurama/ | G13: Y | H13: Hi Vamsi - Plane's Gitea-sync issue has 94 upvotes since 2023, with GitLab parity and Mattermost queued behind it. We can power those syncs so your engineers stay on core PM. Worth a chat?
... A16: Awell | B16: Thomas Vande Casteele | C16: Co-founder & CEO | E16: https://www.linkedin.com/in/thomasvdc/ | G16: Y | H16: Hi Thomas - noticed each EHR integration at Awell is hand-built extension by extension. We offer a self-serve connector catalog so your team stays focused on care flows. Worth a quick chat?
A17: Chainels | B17: Erwin Buckers | C17: Founder & CEO | D17: Target: CEO | E17: https://www.linkedin.com/in/erwin-buckers-35699028/ | F17: High
A18: Chainels | B18: Christiaan Titos Bolivar | C18: Lead Developer - no formal CTO title exists | D18: Target: CTO (closest equiv.) | E18: https://www.linkedin.com/in/christiaan-titos-bolivar-b17550ba/ | F18: Medium
A19: Dockflow | B19: Pauline Van Ostaeyen | C19: Co-Founder - commercial/leadership focus, no one holds literal "CEO" title | D19: Target: CEO (closest equiv.) | E19: https://be.linkedin.com/in/paulinevanostaeyen | F19: Low
A20: Dockflow | B20: Michiel Valee | C20: Co-Founder / Tech Lead | D20: Target: CTO (closest equiv.) | E20: https://be.linkedin.com/in/michielvalee | F20: Medium
A21: EverReal | B21: Nessim Djerboua | C21: CEO & Founder | D21: Target: CEO | E21: https://www.linkedin.com/in/nessimdjerboua/ | F21: High
A22: EverReal | B22: Liviu Ignat | C22: CTO & Co-Founder | D22: Target: CTO | E22: https://www.linkedin.com/in/liviu-ignat-76835b21/ | F22: High
A23: FreightSuite | B23: Samuel Moore | C23: Co-Founder (CEO per third-party org chart) | D23: Target: CEO | E23: https://www.linkedin.com/in/samuel-moore-370767206/ | F23: Medium
A24: FreightSuite | B24: - not confirmed - | C24: William Jacobs is technical co-founder but no source confirms a CTO-equivalent title | D24: Target: CTO | E24: https://uk.linkedin.com/in/william-jacobs-4233665b | F24: Low
A25: Harbor Lab | B25: Antonis Malaxianakis | C25: Founder & CEO | D25: Target: CEO | E25: https://gr.linkedin.com/in/antonis-malaxianakis-7b656b6b | F25: High
A26: Harbor Lab | B26: Spyros Lamprinidis | C26: Chief Technology Officer | D26: Target: CTO | E26: https://www.linkedin.com/in/spyroslambrinidis/ | F26: Medium
A27: HERO Software | B27: Michael Kessler | C27: Founder & CEO (Geschäftsführer) | D27: Target: CEO | E27: https://de.linkedin.com/in/michael-kessler-6201b7a0 | F27: High
A28: HERO Software | B28: Constantin Schomburg | C28: Chief Technology Officer | D28: Target: CTO | E28: https://www.linkedin.com/in/cschomburg/ | F28: High
... A46: Solvimon | B46: Etienne Gerts | C46: Co-Founder & CTO | D46: Target: CTO | E46: https://www.linkedin.com/in/etienne-gerts-91636b4/ | F46: High
A47: Younium | B47: Niclas Lilja | C47: Founder & CEO | E47: https://www.linkedin.com/in/niclas-lilja/ | H47: Hi Niclas - saw a G2 review calling out your Salesforce integration. We help subscription platforms rebuild CRM/ERP sync once and expose every connector mid-market buyers expect. Worth a quick chat?
A48: AgVend | B48: Alexander Reichert | C48: Co-Founder & CEO | E48: https://www.linkedin.com/in/alexanderreichert | H48: Hi Alexander - your grower portals live or die by ERP, agronomy and grain-system syncs. We help teams onboard the next ag ERP without a bespoke build. Open to a quick chat?
A49: AgVend | B49: Eli Rosenberg | C49: Co-Founder & CPO | H49: Hi Eli - following up on integration coverage for AgVend's grower portals (ERP/agronomy/grain-system syncs) - happy to share how we help teams ship these without bespoke builds.
A50: Archy | B50: Jonathan Rat | C50: Co-Founder & CEO | E50: https://www.linkedin.com/in/jonathanrat | H50: Hi Jonathan - sensors, imaging AI and payer systems each need a bespoke connector today. We help teams ship these natively instead of one TWAIN driver at a time. Worth a chat?
A51: Carepatron | B51: Jamie Frew | C51: Co-Founder | E51: https://www.linkedin.com/in/jamie-frew-b843618 | H51: Hi Jamie - Capterra reviewers keep asking Carepatron for Medicare, insurance-billing and accounting integrations. We help teams ship these as embedded, white-label connectors. Open to connecting?
A52: Hona | B52: Matt McClellan | C52: Co-Founder | E52: https://www.linkedin.com/in/matthew-mcclellan22 | H52: Hi Matt - Hona's edge is deep case-management sync with Clio, Filevine and Smokeball. We help teams cover the next ten PMSs prospects ask about, fast. Worth a quick chat?
A53: Hona | B53: Joshua Christensen | C53: Co-Founder & CTO | E53: https://www.linkedin.com/in/joshua-n-christensen | H53: Hi Joshua - curious how the team is scaling PMS integrations beyond Clio/Filevine/Smokeball. We help teams like Hona's ship the long tail of case-management syncs without the bespoke build each time.
A54: Milk Moovement | B54: Jon King | C54: Co-Founder & CEO | E54: https://www.linkedin.com/in/jonathanjking | H54: Hi Jon - saw Milk Moovement ingests lab results via API, FTP or email. We help teams turn that legacy glue into productized, white-label integrations co-ops configure themselves. Worth a chat?
A55: Milk Moovement | B55: Christopher O'Malley | C55: CTO | E55: https://www.linkedin.com/in/comalley | H55: Hi Christopher - curious how the team is productizing lab-result ingestion (API/FTP/email) today. We help teams turn that into self-serve, white-label integrations for co-ops. Open to connecting?
A56: RentCheck | B56: Marco Nelson | C56: Founder & CEO | E56: https://www.linkedin.com/in/marco-nelson-67470530 | H56: Hi Marco - noticed Buildium is still "coming soon" on RentCheck's integrations page. We help teams ship Buildium, Propertyware and the PM long tail in weeks, not quarters. Worth a chat?
A57: RentCheck | B57: Matias Pan | C57: Head of Engineering | E57: https://www.linkedin.com/in/matias-pan-41729a279 | H57: Hi Matias - curious about the roadmap for Buildium/Propertyware and the rest of the PM integration long tail at RentCheck. We help teams ship these in weeks. Open to connecting?
A58: Siteline | B58: Claire Wilson | C58: Co-Founder & CEO | E58: https://www.linkedin.com/in/construction-claire | H58: Hi Claire - saw Siteline maintains 8+ bidirectional construction ERP syncs in-house. We help teams offload that connector maintenance so engineers stay on billing workflows. Worth a chat?
A59: Siteline | B59: Gloria Lin | C59: Co-Founder & CPO | E59: https://www.linkedin.com/in/glo | H59: Hi Gloria - curious how the team is prioritizing the 8+ construction ERP syncs Siteline maintains in-house. We help offload that maintenance so engineering stays on core billing workflows.
A60: VXT | B60: Lucy Turner | C60: Co-Founder & CTO | E60: https://www.linkedin.com/in/lucy-turner-nz | H60: Hi Lucy - VXT ships PMS integrations one announcement at a time today. We help legal-tech teams cover the PMS long tail all at once instead of one-off builds. Worth a quick chat?
A61: Dash0 | B61: Mirko Novakovic | C61: CEO | E61: https://www.linkedin.com/in/mirkonovakovic | H61: Hi Mirko - Dash0 has 103 ingestion integrations but alerts only reach PagerDuty and a bare Slack webhook. We help teams get Datadog-grade outbound reach in a quarter. Worth a chat?
... A90: SPRY | B90: Brijraj Bhuptani | C90: Co-Founder & CEO | E90: https://www.linkedin.com/in/brijraj-bhuptani-a6624a | H90: Hi Brijraj - enterprise rehab deals bring EHR and clearinghouse integration asks along with them. Curious how SPRY is saying yes to those without pulling engineers off the core EMR. Would love to compare notes.
A91: Rentlio | B91: Ivan Padavić | C91: CTO and co-founder
A92: Rentlio | B92: Marko Mišulić | C92: CEO and co-founder
A93: Lemax | B93: Marko Elezović | C93: CTO / Head of Engineering (may have moved on) | E93: https://hr.linkedin.com/in/melezov
A94: Lemax | B94: Mate Kostovski | C94: CEO
A95: AGRIVI | B95: Matija Žulj | C95: Founder and CEO | E95: https://www.linkedin.com/in/matijazulj/
A96: Nokumo | B96: Marko Brković | C96: CTO
A97: Nokumo | B97: Nikola Crnković | C97: CPO / CRO
A98: Mireo | B98: Ivica Siladić | C98: CTO and co-founder
A99: DotYourSpot | B99: Karlo Đuderija | C99: CTO and co-founder
A100: DotYourSpot | B100: Zlatko Kovačić | C100: CEO and founder
A101: MMK Systems (Booking Manager) | B101: Marko Gnjidić | C101: Founder and CEO
A102: NauSYS (Stratus IT) | B102: Goran Pavešić | C102: CEO and co-founder
A103: NauSYS (Stratus IT) | B103: Luka Surija | C103: CTO
A104: Bitreport | B104: Domagoj Rade | C104: CTO and co-founder | E104: https://www.linkedin.com/in/domagoj-rade-ab1485198/
A105: Bitreport | B105: Marko Čačić | C105: CEO and co-founder
A106: Productive | B106: Tomislav Car | C106: Founder and CEO | E106: https://www.linkedin.com/in/tomislavcar/
A107: Productive | B107: Ivan Lučin | C107: VP Engineering | E107: https://www.linkedin.com/in/ivanlucin/
A108: Farseer | B108: Luka Mijatović | C108: Co-founder and CTO | E108: https://www.linkedin.com/in/lukamijatovic/
A109: Farseer | B109: Matija Nakić | C109: Co-founder and CEO
A110: TalentLyft | B110: Nikola Biondić | C110: Co-founder and CTO (headline now reads "Hidden Talent"; check) | E110: https://www.linkedin.com/in/biondic/
A111: TalentLyft | B111: Mario Buntić | C111: Co-founder and CEO
A112: Oradian | B112: Rikard Pavelić | C112: CTO (a CTO search is open)
A113: Oradian | B113: Antonio Separović | C113: CEO and co-founder
A114: OptimoRoute | B114: Frane Šarić | C114: Co-founder and CTO
A115: OptimoRoute | B115: Goran Kukolj | C115: Co-founder | E115: https://www.linkedin.com/in/gorankukolj/
A116: Hypefy | B116: Stjepan Zelić | C116: Co-founder and CEO
A117: Hypefy | B117: Filip Špiranec / Davor Šibenik | C117: CTO (sources disagree on which)
A118: Determ | B118: Tomislav Grubišić | C118: Co-founder and CEO
A119: Treblle | B119: Vedran Cindrić | C119: Founder and CEO | E119: https://www.linkedin.com/in/vedrancindric/
A120: Legit (Data Privacy Manager) | B120: Marijan Bračić | C120: Board president (strategy, R&D, product)
A121: Tomsoft (Luceed ERP) | B121: Tomislav Ivančević | C121: Founder and director | E121: https://www.linkedin.com/in/tomislav-ivancevic/
A122: Micronic (KISERP / KIS4WIN) | B122: Igor Janjić | C122: Management board member
A123: E-RAČUNI | B123: David Gorišek | C123: Founder and director
A124: ViziBit (Vizibit eRačun) | B124: Robert Vurušić | C124: Founder and CEO
A125: RIS (Faros ERP, Ensolva) | B125: Mile Pavlić | C125: Founder and CEO
A126: Pupilla (Synesis) | B126: Krunoslav Lisac | C126: Founder and director
A127: Pondi (ePoslovanje) | B127: Domagoj Bikić | C127: Founder and director
A128: 4th Dimension (4D Wand) | B128: Edin Čahtarević | C128: Director
A129: BillKO (Kupuj Online d.o.o.) | B129: Emir Dizdarević | C129: Founder, sole member and board member (Web Studio / WSPay founder)

Sheet Notes
A1: HOW TO USE THIS WORKBOOK
A2: Targets: one row per company (101). Research columns came from the July target list (+ Croatia segment, Oct 4). Yellow columns are yours to fill in as outreach runs. Row 2 is the example row from the old tracker.
A3: Contacts: one row per person, joined to Targets by company name. n_contacts on Targets counts them. followed_on_linkedin = Y for the 15 contacts listed under "Followed from 15" in the old tracker.
A4: first_line = the shorter hook from the tracker. research_hook = the original hook from the research doc. Re-verify the underlying fact before sending either.
A5: Below: methodology, caveats, wave plans, low-confidence lists and exclusions from bytechef-embedded-target-list-2026-07.md (tables moved into the other tabs).
A7: ByteChef Embedded - Outbound Target List (first cut)
A9: Date: July 28, 2026 (Croatia segment added October 4, 2026) · Companies: 101 across 5 segments · Purpose: GTM strategy §7.3 - the 90-day embedded validation sprint's outreach list.
A11: How this list was built
A13: Four parallel research passes (EU vertical SaaS · US/RoW vertical SaaS · dev tools & horizontal B2B · HR/fin-ops/accounting) against the §7.3 criteria: B2B SaaS, seed–Series B, ~10–200 employees, demonstrated integration pain, verticals whose customers demand integrations. Competitors (iPaaS / unified-API / workflow-automation vendors) and Series C+ / >300-employee companies were excluded.
A15: Scoring rubric (per company, /10): Stage fit 0–2 · Size fit 0–2 · Pain evidence 0–3 · Vertical fit 0–2 · EU bonus +1 (applied to European HQs incl. UK - deduct 1 for strict EU-27).
A17: Global caveats - read before sending anything:
A18: 1. Most companies' /integrations pages blocked automated fetching (403). "Thin page" judgments rest on review sites, support docs, changelogs, and search-indexed copy. Verify each company's current integrations page manually before citing it in an email.
... A157: - No qualifying candidates found in Croatian legal, education or energy SaaS.
